<?xml version='1.0' encoding='utf-8'?>
<q:quakeml xmlns="http://quakeml.org/xmlns/bed/1.2" xmlns:q="http://quakeml.org/xmlns/quakeml/1.2" xmlns:ns0="http://anss.org/xmlns/catalog/0.1">
  <eventParameters publicID="smi:local/fb1bde6c-0ba7-4a4f-b7e8-cf00189b33ca">
    <event publicID="quakeml:service.scedc.caltech.edu/fdsnws/event/1/query?eventid=40834015" ns0:datasource="ci" ns0:dataid="ci40834015" ns0:eventsource="ci" ns0:eventid="40834015">
      <preferredOriginID>quakeml:service.scedc.caltech.edu/fdsnws/event/1/query?originid=105807397</preferredOriginID>
      <preferredMagnitudeID>quakeml:service.scedc.caltech.edu/fdsnws/event/1/query?magnitudeid=109259621</preferredMagnitudeID>
      <type>earthquake</type>
      <creationInfo>
        <agencyID>CI</agencyID>
        <agencyURI>quakeml:doi.org/10.7909/C3WD3xH1</agencyURI>
        <creationTime>2025-01-05T04:35:57.000000Z</creationTime>
        <version>5</version>
      </creationInfo>
      <origin publicID="quakeml:service.scedc.caltech.edu/fdsnws/event/1/query?originid=105807397" ns0:datasource="ci" ns0:dataid="ci40834015" ns0:eventsource="ci" ns0:eventid="40834015">
        <time>
          <value>2025-01-05T04:31:26.920000Z</value>
        </time>
        <latitude>
          <value>33.6506667</value>
        </latitude>
        <longitude>
          <value>-116.7073333</value>
        </longitude>
        <depth>
          <value>15860.0</value>
          <uncertainty>410.0</uncertainty>
        </depth>
        <depthType>from location</depthType>
        <timeFixed>false</timeFixed>
        <epicenterFixed>false</epicenterFixed>
        <methodID>smi:ci.anss.org/origin/HYP2000</methodID>
        <quality>
          <associatedPhaseCount>40</associatedPhaseCount>
          <usedPhaseCount>40</usedPhaseCount>
          <associatedStationCount>25</associatedStationCount>
          <usedStationCount>25</usedStationCount>
          <standardError>0.13</standardError>
          <azimuthalGap>58.0</azimuthalGap>
          <secondaryAzimuthalGap>408.0</secondaryAzimuthalGap>
          <minimumDistance>0.06338</minimumDistance>
          <maximumDistance>0.5778</maximumDistance>
          <medianDistance>0.275</medianDistance>
        </quality>
        <type>hypocenter</type>
        <evaluationMode>manual</evaluationMode>
        <evaluationStatus>final</evaluationStatus>
        <creationInfo>
          <agencyID>CI</agencyID>
          <creationTime>2025-01-05T04:35:42.000000Z</creationTime>
        </creationInfo>
        <originUncertainty>
          <preferredDescription>confidence ellipsoid</preferredDescription>
          <horizontalUncertainty>200.0</horizontalUncertainty>
          <confidenceLevel>95.0</confidenceLevel>
          <confidenceEllipsoid>
            <semiMajorAxisLength>1008.0</semiMajorAxisLength>
            <semiMinorAxisLength>456.0</semiMinorAxisLength>
            <semiIntermediateAxisLength>504.0</semiIntermediateAxisLength>
            <majorAxisPlunge>77.0</majorAxisPlunge>
            <majorAxisAzimuth>352.0</majorAxisAzimuth>
            <majorAxisRotation>34.0</majorAxisRotation>
          </confidenceEllipsoid>
        </originUncertainty>
        <arrival publicID="quakeml:service.scedc.caltech.edu/fdsnws/event/1/query?assocaro=144511383">
          <pickID>quakeml:service.scedc.caltech.edu/fdsnws/event/1/query?assocaro=144511383</pickID>
          <phase>P</phase>
          <timeCorrection>-0.08</timeCorrection>
          <azimuth>150.0</azimuth>
          <distance>0.1786</distance>
          <takeoffAngle>
            <value>125.0</value>
          </takeoffAngle>
          <timeResidual>0.14</timeResidual>
          <timeWeight>0.12</timeWeight>
          <creationInfo>
            <agencyID>CI</agencyID>
            <creationTime>2025-01-05T04:35:42.000000Z</creationTime>
          </creationInfo>
        </arrival>
        <arrival publicID="quakeml:service.scedc.caltech.edu/fdsnws/event/1/query?assocaro=144511431">
          <pickID>quakeml:service.scedc.caltech.edu/fdsnws/event/1/query?assocaro=144511431</pickID>
          <phase>S</phase>
          <timeCorrection>-0.42</timeCorrection>
          <azimuth>244.0</azimuth>
          <distance>0.4322</distance>
          <takeoffAngle>
            <value>100.0</value>
          </takeoffAngle>
          <timeResidual>0.09</timeResidual>
          <timeWeight>0.06</timeWeight>
          <creationInfo>
            <agencyID>CI</agencyID>
            <creationTime>2025-01-05T04:35:42.000000Z</creationTime>
          </creationInfo>
        </arrival>
        <arrival publicID="quakeml:service.scedc.caltech.edu/fdsnws/event/1/query?assocaro=144511543">
          <pickID>quakeml:service.scedc.caltech.edu/fdsnws/event/1/query?assocaro=144511543</pickID>
          <phase>S</phase>
          <timeCorrection>-0.36</timeCorrection>
          <azimuth>282.0</azimuth>
          <distance>0.1842</distance>
          <takeoffAngle>
            <value>124.0</value>
          </takeoffAngle>
          <timeResidual>0.29</timeResidual>
          <timeWeight>0.12</timeWeight>
          <creationInfo>
            <agencyID>CI</agencyID>
            <creationTime>2025-01-05T04:35:42.000000Z</creationTime>
          </creationInfo>
        </arrival>
        <arrival publicID="quakeml:service.scedc.caltech.edu/fdsnws/event/1/query?assocaro=266266501">
          <pickID>quakeml:service.scedc.caltech.edu/fdsnws/event/1/query?assocaro=266266501</pickID>
          <phase>P</phase>
          <timeCorrection>-0.17</timeCorrection>
          <azimuth>357.0</azimuth>
          <distance>0.06338</distance>
          <takeoffAngle>
            <value>155.0</value>
          </takeoffAngle>
          <timeResidual>0.01</timeResidual>
          <timeWeight>0.23</timeWeight>
          <creationInfo>
            <agencyID>CI</agencyID>
            <creationTime>2025-01-05T04:35:42.000000Z</creationTime>
          </creationInfo>
        </arrival>
        <arrival publicID="quakeml:service.scedc.caltech.edu/fdsnws/event/1/query?assocaro=266266509">
          <pickID>quakeml:service.scedc.caltech.edu/fdsnws/event/1/query?assocaro=266266509</pickID>
          <phase>S</phase>
          <timeCorrection>-0.47</timeCorrection>
          <azimuth>357.0</azimuth>
          <distance>0.06338</distance>
          <takeoffAngle>
            <value>155.0</value>
          </takeoffAngle>
          <timeResidual>0.25</timeResidual>
          <timeWeight>0.09</timeWeight>
          <creationInfo>
            <agencyID>CI</agencyID>
            <creationTime>2025-01-05T04:35:42.000000Z</creationTime>
          </creationInfo>
        </arrival>
        <arrival publicID="quakeml:service.scedc.caltech.edu/fdsnws/event/1/query?assocaro=266266517">
          <pickID>quakeml:service.scedc.caltech.edu/fdsnws/event/1/query?assocaro=266266517</pickID>
          <phase>P</phase>
          <timeCorrection>-0.08</timeCorrection>
          <azimuth>197.0</azimuth>
          <distance>0.08864</distance>
          <takeoffAngle>
            <value>147.0</value>
          </takeoffAngle>
          <timeResidual>-0.02</timeResidual>
          <timeWeight>0.18</timeWeight>
          <creationInfo>
            <agencyID>CI</agencyID>
            <creationTime>2025-01-05T04:35:42.000000Z</creationTime>
          </creationInfo>
        </arrival>
        <arrival publicID="quakeml:service.scedc.caltech.edu/fdsnws/event/1/query?assocaro=266266525">
          <pickID>quakeml:service.scedc.caltech.edu/fdsnws/event/1/query?assocaro=266266525</pickID>
          <phase>S</phase>
          <timeCorrection>-0.33</timeCorrection>
          <azimuth>197.0</azimuth>
          <distance>0.08864</distance>
          <takeoffAngle>
            <value>147.0</value>
          </takeoffAngle>
          <timeResidual>0.3</timeResidual>
          <timeWeight>0.06</timeWeight>
          <creationInfo>
            <agencyID>CI</agencyID>
            <creationTime>2025-01-05T04:35:42.000000Z</creationTime>
          </creationInfo>
        </arrival>
        <arrival publicID="quakeml:service.scedc.caltech.edu/fdsnws/event/1/query?assocaro=266266533">
          <pickID>quakeml:service.scedc.caltech.edu/fdsnws/event/1/query?assocaro=266266533</pickID>
          <phase>P</phase>
          <timeCorrection>0.0</timeCorrection>
          <azimuth>93.0</azimuth>
          <distance>0.09343</distance>
          <takeoffAngle>
            <value>145.0</value>
          </takeoffAngle>
          <timeResidual>-0.13</timeResidual>
          <timeWeight>0.23</timeWeight>
          <creationInfo>
            <agencyID>CI</agencyID>
            <creationTime>2025-01-05T04:35:42.000000Z</creationTime>
          </creationInfo>
        </arrival>
        <arrival publicID="quakeml:service.scedc.caltech.edu/fdsnws/event/1/query?assocaro=266266541">
          <pickID>quakeml:service.scedc.caltech.edu/fdsnws/event/1/query?assocaro=266266541</pickID>
          <phase>S</phase>
          <timeCorrection>0.0</timeCorrection>
          <azimuth>93.0</azimuth>
          <distance>0.09343</distance>
          <takeoffAngle>
            <value>146.0</value>
          </takeoffAngle>
          <timeResidual>-0.12</timeResidual>
          <timeWeight>0.06</timeWeight>
          <creationInfo>
            <agencyID>CI</agencyID>
            <creationTime>2025-01-05T04:35:42.000000Z</creationTime>
          </creationInfo>
        </arrival>
        <arrival publicID="quakeml:service.scedc.caltech.edu/fdsnws/event/1/query?assocaro=266266549">
          <pickID>quakeml:service.scedc.caltech.edu/fdsnws/event/1/query?assocaro=266266549</pickID>
          <phase>P</phase>
          <timeCorrection>-0.16</timeCorrection>
          <azimuth>357.0</azimuth>
          <distance>0.09574</distance>
          <takeoffAngle>
            <value>145.0</value>
          </takeoffAngle>
          <timeResidual>0.43</timeResidual>
          <timeWeight>0.12</timeWeight>
          <creationInfo>
            <agencyID>CI</agencyID>
            <creationTime>2025-01-05T04:35:42.000000Z</creationTime>
          </creationInfo>
        </arrival>
        <arrival publicID="quakeml:service.scedc.caltech.edu/fdsnws/event/1/query?assocaro=266266557">
          <pickID>quakeml:service.scedc.caltech.edu/fdsnws/event/1/query?assocaro=266266557</pickID>
          <phase>P</phase>
          <timeCorrection>-0.02</timeCorrection>
          <azimuth>142.0</azimuth>
          <distance>0.1055</distance>
          <takeoffAngle>
            <value>142.0</value>
          </takeoffAngle>
          <timeResidual>0.16</timeResidual>
          <timeWeight>0.18</timeWeight>
          <creationInfo>
            <agencyID>CI</agencyID>
            <creationTime>2025-01-05T04:35:42.000000Z</creationTime>
          </creationInfo>
        </arrival>
        <arrival publicID="quakeml:service.scedc.caltech.edu/fdsnws/event/1/query?assocaro=266266565">
          <pickID>quakeml:service.scedc.caltech.edu/fdsnws/event/1/query?assocaro=266266565</pickID>
          <phase>S</phase>
          <timeCorrection>-0.07</timeCorrection>
          <azimuth>142.0</azimuth>
          <distance>0.1055</distance>
          <takeoffAngle>
            <value>142.0</value>
          </takeoffAngle>
          <timeResidual>0.66</timeResidual>
          <timeWeight>0.06</timeWeight>
          <creationInfo>
            <agencyID>CI</agencyID>
            <creationTime>2025-01-05T04:35:42.000000Z</creationTime>
          </creationInfo>
        </arrival>
        <arrival publicID="quakeml:service.scedc.caltech.edu/fdsnws/event/1/query?assocaro=266266573">
          <pickID>quakeml:service.scedc.caltech.edu/fdsnws/event/1/query?assocaro=266266573</pickID>
          <phase>P</phase>
          <timeCorrection>-0.12</timeCorrection>
          <azimuth>261.0</azimuth>
          <distance>0.119</distance>
          <takeoffAngle>
            <value>138.0</value>
          </takeoffAngle>
          <timeResidual>-0.03</timeResidual>
          <timeWeight>0.12</timeWeight>
          <creationInfo>
            <agencyID>CI</agencyID>
            <creationTime>2025-01-05T04:35:42.000000Z</creationTime>
          </creationInfo>
        </arrival>
        <arrival publicID="quakeml:service.scedc.caltech.edu/fdsnws/event/1/query?assocaro=266266581">
          <pickID>quakeml:service.scedc.caltech.edu/fdsnws/event/1/query?assocaro=266266581</pickID>
          <phase>S</phase>
          <timeCorrection>-0.18</timeCorrection>
          <azimuth>261.0</azimuth>
          <distance>0.119</distance>
          <takeoffAngle>
            <value>138.0</value>
          </takeoffAngle>
          <timeResidual>0.01</timeResidual>
          <timeWeight>0.06</timeWeight>
          <creationInfo>
            <agencyID>CI</agencyID>
            <creationTime>2025-01-05T04:35:42.000000Z</creationTime>
          </creationInfo>
        </arrival>
        <arrival publicID="quakeml:service.scedc.caltech.edu/fdsnws/event/1/query?assocaro=266266589">
          <pickID>quakeml:service.scedc.caltech.edu/fdsnws/event/1/query?assocaro=266266589</pickID>
          <phase>P</phase>
          <timeCorrection>0.0</timeCorrection>
          <azimuth>210.0</azimuth>
          <distance>0.1695</distance>
          <takeoffAngle>
            <value>126.0</value>
          </takeoffAngle>
          <timeResidual>-0.12</timeResidual>
          <timeWeight>0.23</timeWeight>
          <creationInfo>
            <agencyID>CI</agencyID>
            <creationTime>2025-01-05T04:35:42.000000Z</creationTime>
          </creationInfo>
        </arrival>
        <arrival publicID="quakeml:service.scedc.caltech.edu/fdsnws/event/1/query?assocaro=266266597">
          <pickID>quakeml:service.scedc.caltech.edu/fdsnws/event/1/query?assocaro=266266597</pickID>
          <phase>S</phase>
          <timeCorrection>0.0</timeCorrection>
          <azimuth>210.0</azimuth>
          <distance>0.1695</distance>
          <takeoffAngle>
            <value>127.0</value>
          </takeoffAngle>
          <timeResidual>-0.19</timeResidual>
          <timeWeight>0.06</timeWeight>
          <creationInfo>
            <agencyID>CI</agencyID>
            <creationTime>2025-01-05T04:35:42.000000Z</creationTime>
          </creationInfo>
        </arrival>
        <arrival publicID="quakeml:service.scedc.caltech.edu/fdsnws/event/1/query?assocaro=266266605">
          <pickID>quakeml:service.scedc.caltech.edu/fdsnws/event/1/query?assocaro=266266605</pickID>
          <phase>P</phase>
          <timeCorrection>-0.08</timeCorrection>
          <azimuth>338.0</azimuth>
          <distance>0.1973</distance>
          <takeoffAngle>
            <value>121.0</value>
          </takeoffAngle>
          <timeResidual>-0.04</timeResidual>
          <timeWeight>0.12</timeWeight>
          <creationInfo>
            <agencyID>CI</agencyID>
            <creationTime>2025-01-05T04:35:42.000000Z</creationTime>
          </creationInfo>
        </arrival>
        <arrival publicID="quakeml:service.scedc.caltech.edu/fdsnws/event/1/query?assocaro=266266613">
          <pickID>quakeml:service.scedc.caltech.edu/fdsnws/event/1/query?assocaro=266266613</pickID>
          <phase>S</phase>
          <timeCorrection>-0.25</timeCorrection>
          <azimuth>338.0</azimuth>
          <distance>0.1973</distance>
          <takeoffAngle>
            <value>122.0</value>
          </takeoffAngle>
          <timeResidual>0.25</timeResidual>
          <timeWeight>0.06</timeWeight>
          <creationInfo>
            <agencyID>CI</agencyID>
            <creationTime>2025-01-05T04:35:42.000000Z</creationTime>
          </creationInfo>
        </arrival>
        <arrival publicID="quakeml:service.scedc.caltech.edu/fdsnws/event/1/query?assocaro=266266621">
          <pickID>quakeml:service.scedc.caltech.edu/fdsnws/event/1/query?assocaro=266266621</pickID>
          <phase>P</phase>
          <timeCorrection>-0.15</timeCorrection>
          <azimuth>284.0</azimuth>
          <distance>0.2519</distance>
          <takeoffAngle>
            <value>113.0</value>
          </takeoffAngle>
          <timeResidual>0.06</timeResidual>
          <timeWeight>0.12</timeWeight>
          <creationInfo>
            <agencyID>CI</agencyID>
            <creationTime>2025-01-05T04:35:42.000000Z</creationTime>
          </creationInfo>
        </arrival>
        <arrival publicID="quakeml:service.scedc.caltech.edu/fdsnws/event/1/query?assocaro=266266629">
          <pickID>quakeml:service.scedc.caltech.edu/fdsnws/event/1/query?assocaro=266266629</pickID>
          <phase>S</phase>
          <timeCorrection>-0.34</timeCorrection>
          <azimuth>284.0</azimuth>
          <distance>0.2519</distance>
          <takeoffAngle>
            <value>114.0</value>
          </takeoffAngle>
          <timeResidual>0.31</timeResidual>
          <timeWeight>0.06</timeWeight>
          <creationInfo>
            <agencyID>CI</agencyID>
            <creationTime>2025-01-05T04:35:42.000000Z</creationTime>
          </creationInfo>
        </arrival>
        <arrival publicID="quakeml:service.scedc.caltech.edu/fdsnws/event/1/query?assocaro=266266637">
          <pickID>quakeml:service.scedc.caltech.edu/fdsnws/event/1/query?assocaro=266266637</pickID>
          <phase>P</phase>
          <timeCorrection>-0.17</timeCorrection>
          <azimuth>270.0</azimuth>
          <distance>0.252</distance>
          <takeoffAngle>
            <value>113.0</value>
          </takeoffAngle>
          <timeResidual>-0.04</timeResidual>
          <timeWeight>0.18</timeWeight>
          <creationInfo>
            <agencyID>CI</agencyID>
            <creationTime>2025-01-05T04:35:42.000000Z</creationTime>
          </creationInfo>
        </arrival>
        <arrival publicID="quakeml:service.scedc.caltech.edu/fdsnws/event/1/query?assocaro=266266645">
          <pickID>quakeml:service.scedc.caltech.edu/fdsnws/event/1/query?assocaro=266266645</pickID>
          <phase>S</phase>
          <timeCorrection>-0.43</timeCorrection>
          <azimuth>270.0</azimuth>
          <distance>0.252</distance>
          <takeoffAngle>
            <value>114.0</value>
          </takeoffAngle>
          <timeResidual>0.08</timeResidual>
          <timeWeight>0.06</timeWeight>
          <creationInfo>
            <agencyID>CI</agencyID>
            <creationTime>2025-01-05T04:35:42.000000Z</creationTime>
          </creationInfo>
        </arrival>
        <arrival publicID="quakeml:service.scedc.caltech.edu/fdsnws/event/1/query?assocaro=266266653">
          <pickID>quakeml:service.scedc.caltech.edu/fdsnws/event/1/query?assocaro=266266653</pickID>
          <phase>P</phase>
          <timeCorrection>-0.18</timeCorrection>
          <azimuth>90.0</azimuth>
          <distance>0.275</distance>
          <takeoffAngle>
            <value>111.0</value>
          </takeoffAngle>
          <timeResidual>-0.1</timeResidual>
          <timeWeight>0.23</timeWeight>
          <creationInfo>
            <agencyID>CI</agencyID>
            <creationTime>2025-01-05T04:35:42.000000Z</creationTime>
          </creationInfo>
        </arrival>
        <arrival publicID="quakeml:service.scedc.caltech.edu/fdsnws/event/1/query?assocaro=266266661">
          <pickID>quakeml:service.scedc.caltech.edu/fdsnws/event/1/query?assocaro=266266661</pickID>
          <phase>S</phase>
          <timeCorrection>-0.46</timeCorrection>
          <azimuth>90.0</azimuth>
          <distance>0.275</distance>
          <takeoffAngle>
            <value>112.0</value>
          </takeoffAngle>
          <timeResidual>0.03</timeResidual>
          <timeWeight>0.06</timeWeight>
          <creationInfo>
            <agencyID>CI</agencyID>
            <creationTime>2025-01-05T04:35:42.000000Z</creationTime>
          </creationInfo>
        </arrival>
        <arrival publicID="quakeml:service.scedc.caltech.edu/fdsnws/event/1/query?assocaro=266266669">
          <pickID>quakeml:service.scedc.caltech.edu/fdsnws/event/1/query?assocaro=266266669</pickID>
          <phase>P</phase>
          <timeCorrection>-0.18</timeCorrection>
          <azimuth>263.0</azimuth>
          <distance>0.2807</distance>
          <takeoffAngle>
            <value>110.0</value>
          </takeoffAngle>
          <timeResidual>-0.05</timeResidual>
          <timeWeight>0.12</timeWeight>
          <creationInfo>
            <agencyID>CI</agencyID>
            <creationTime>2025-01-05T04:35:42.000000Z</creationTime>
          </creationInfo>
        </arrival>
        <arrival publicID="quakeml:service.scedc.caltech.edu/fdsnws/event/1/query?assocaro=266266677">
          <pickID>quakeml:service.scedc.caltech.edu/fdsnws/event/1/query?assocaro=266266677</pickID>
          <phase>P</phase>
          <timeCorrection>-0.03</timeCorrection>
          <azimuth>157.0</azimuth>
          <distance>0.3222</distance>
          <takeoffAngle>
            <value>106.0</value>
          </takeoffAngle>
          <timeResidual>0.09</timeResidual>
          <timeWeight>0.23</timeWeight>
          <creationInfo>
            <agencyID>CI</agencyID>
            <creationTime>2025-01-05T04:35:42.000000Z</creationTime>
          </creationInfo>
        </arrival>
        <arrival publicID="quakeml:service.scedc.caltech.edu/fdsnws/event/1/query?assocaro=266266685">
          <pickID>quakeml:service.scedc.caltech.edu/fdsnws/event/1/query?assocaro=266266685</pickID>
          <phase>S</phase>
          <timeCorrection>-0.2</timeCorrection>
          <azimuth>157.0</azimuth>
          <distance>0.3222</distance>
          <takeoffAngle>
            <value>107.0</value>
          </takeoffAngle>
          <timeResidual>0.32</timeResidual>
          <timeWeight>0.06</timeWeight>
          <creationInfo>
            <agencyID>CI</agencyID>
            <creationTime>2025-01-05T04:35:42.000000Z</creationTime>
          </creationInfo>
        </arrival>
        <arrival publicID="quakeml:service.scedc.caltech.edu/fdsnws/event/1/query?assocaro=266266693">
          <pickID>quakeml:service.scedc.caltech.edu/fdsnws/event/1/query?assocaro=266266693</pickID>
          <phase>P</phase>
          <timeCorrection>-0.11</timeCorrection>
          <azimuth>204.0</azimuth>
          <distance>0.3234</distance>
          <takeoffAngle>
            <value>106.0</value>
          </takeoffAngle>
          <timeResidual>0.03</timeResidual>
          <timeWeight>0.12</timeWeight>
          <creationInfo>
            <agencyID>CI</agencyID>
            <creationTime>2025-01-05T04:35:42.000000Z</creationTime>
          </creationInfo>
        </arrival>
        <arrival publicID="quakeml:service.scedc.caltech.edu/fdsnws/event/1/query?assocaro=266266701">
          <pickID>quakeml:service.scedc.caltech.edu/fdsnws/event/1/query?assocaro=266266701</pickID>
          <phase>S</phase>
          <timeCorrection>-0.28</timeCorrection>
          <azimuth>204.0</azimuth>
          <distance>0.3234</distance>
          <takeoffAngle>
            <value>107.0</value>
          </takeoffAngle>
          <timeResidual>0.28</timeResidual>
          <timeWeight>0.06</timeWeight>
          <creationInfo>
            <agencyID>CI</agencyID>
            <creationTime>2025-01-05T04:35:42.000000Z</creationTime>
          </creationInfo>
        </arrival>
        <arrival publicID="quakeml:service.scedc.caltech.edu/fdsnws/event/1/query?assocaro=266266709">
          <pickID>quakeml:service.scedc.caltech.edu/fdsnws/event/1/query?assocaro=266266709</pickID>
          <phase>S</phase>
          <timeCorrection>-0.29</timeCorrection>
          <azimuth>227.0</azimuth>
          <distance>0.3763</distance>
          <takeoffAngle>
            <value>103.0</value>
          </takeoffAngle>
          <timeResidual>0.87</timeResidual>
          <timeWeight>0.02</timeWeight>
          <creationInfo>
            <agencyID>CI</agencyID>
            <creationTime>2025-01-05T04:35:42.000000Z</creationTime>
          </creationInfo>
        </arrival>
        <arrival publicID="quakeml:service.scedc.caltech.edu/fdsnws/event/1/query?assocaro=266266717">
          <pickID>quakeml:service.scedc.caltech.edu/fdsnws/event/1/query?assocaro=266266717</pickID>
          <phase>P</phase>
          <timeCorrection>-0.01</timeCorrection>
          <azimuth>7.0</azimuth>
          <distance>0.39</distance>
          <takeoffAngle>
            <value>100.0</value>
          </takeoffAngle>
          <timeResidual>0.08</timeResidual>
          <timeWeight>0.12</timeWeight>
          <creationInfo>
            <agencyID>CI</agencyID>
            <creationTime>2025-01-05T04:35:42.000000Z</creationTime>
          </creationInfo>
        </arrival>
        <arrival publicID="quakeml:service.scedc.caltech.edu/fdsnws/event/1/query?assocaro=266266725">
          <pickID>quakeml:service.scedc.caltech.edu/fdsnws/event/1/query?assocaro=266266725</pickID>
          <phase>S</phase>
          <timeCorrection>-0.03</timeCorrection>
          <azimuth>7.0</azimuth>
          <distance>0.39</distance>
          <takeoffAngle>
            <value>102.0</value>
          </takeoffAngle>
          <timeResidual>0.45</timeResidual>
          <timeWeight>0.03</timeWeight>
          <creationInfo>
            <agencyID>CI</agencyID>
            <creationTime>2025-01-05T04:35:42.000000Z</creationTime>
          </creationInfo>
        </arrival>
        <arrival publicID="quakeml:service.scedc.caltech.edu/fdsnws/event/1/query?assocaro=266266733">
          <pickID>quakeml:service.scedc.caltech.edu/fdsnws/event/1/query?assocaro=266266733</pickID>
          <phase>P</phase>
          <timeCorrection>-0.07</timeCorrection>
          <azimuth>186.0</azimuth>
          <distance>0.4158</distance>
          <takeoffAngle>
            <value>99.0</value>
          </takeoffAngle>
          <timeResidual>-0.02</timeResidual>
          <timeWeight>0.12</timeWeight>
          <creationInfo>
            <agencyID>CI</agencyID>
            <creationTime>2025-01-05T04:35:42.000000Z</creationTime>
          </creationInfo>
        </arrival>
        <arrival publicID="quakeml:service.scedc.caltech.edu/fdsnws/event/1/query?assocaro=266266741">
          <pickID>quakeml:service.scedc.caltech.edu/fdsnws/event/1/query?assocaro=266266741</pickID>
          <phase>S</phase>
          <timeCorrection>0.0</timeCorrection>
          <azimuth>130.0</azimuth>
          <distance>0.4394</distance>
          <takeoffAngle>
            <value>99.0</value>
          </takeoffAngle>
          <timeResidual>0.0</timeResidual>
          <timeWeight>0.03</timeWeight>
          <creationInfo>
            <agencyID>CI</agencyID>
            <creationTime>2025-01-05T04:35:42.000000Z</creationTime>
          </creationInfo>
        </arrival>
        <arrival publicID="quakeml:service.scedc.caltech.edu/fdsnws/event/1/query?assocaro=266266749">
          <pickID>quakeml:service.scedc.caltech.edu/fdsnws/event/1/query?assocaro=266266749</pickID>
          <phase>P</phase>
          <timeCorrection>-0.05</timeCorrection>
          <azimuth>173.0</azimuth>
          <distance>0.4531</distance>
          <takeoffAngle>
            <value>97.0</value>
          </takeoffAngle>
          <timeResidual>0.02</timeResidual>
          <timeWeight>0.12</timeWeight>
          <creationInfo>
            <agencyID>CI</agencyID>
            <creationTime>2025-01-05T04:35:42.000000Z</creationTime>
          </creationInfo>
        </arrival>
        <arrival publicID="quakeml:service.scedc.caltech.edu/fdsnws/event/1/query?assocaro=266266757">
          <pickID>quakeml:service.scedc.caltech.edu/fdsnws/event/1/query?assocaro=266266757</pickID>
          <phase>S</phase>
          <timeCorrection>-0.25</timeCorrection>
          <azimuth>173.0</azimuth>
          <distance>0.4531</distance>
          <takeoffAngle>
            <value>99.0</value>
          </takeoffAngle>
          <timeResidual>0.37</timeResidual>
          <timeWeight>0.06</timeWeight>
          <creationInfo>
            <agencyID>CI</agencyID>
            <creationTime>2025-01-05T04:35:42.000000Z</creationTime>
          </creationInfo>
        </arrival>
        <arrival publicID="quakeml:service.scedc.caltech.edu/fdsnws/event/1/query?assocaro=266266765">
          <pickID>quakeml:service.scedc.caltech.edu/fdsnws/event/1/query?assocaro=266266765</pickID>
          <phase>P</phase>
          <timeCorrection>-0.02</timeCorrection>
          <azimuth>32.0</azimuth>
          <distance>0.4941</distance>
          <takeoffAngle>
            <value>95.0</value>
          </takeoffAngle>
          <timeResidual>1.11</timeResidual>
          <timeWeight>0.01</timeWeight>
          <creationInfo>
            <agencyID>CI</agencyID>
            <creationTime>2025-01-05T04:35:42.000000Z</creationTime>
          </creationInfo>
        </arrival>
        <arrival publicID="quakeml:service.scedc.caltech.edu/fdsnws/event/1/query?assocaro=266266773">
          <pickID>quakeml:service.scedc.caltech.edu/fdsnws/event/1/query?assocaro=266266773</pickID>
          <phase>S</phase>
          <timeCorrection>-0.14</timeCorrection>
          <azimuth>32.0</azimuth>
          <distance>0.4941</distance>
          <takeoffAngle>
            <value>97.0</value>
          </takeoffAngle>
          <timeResidual>0.57</timeResidual>
          <timeWeight>0.03</timeWeight>
          <creationInfo>
            <agencyID>CI</agencyID>
            <creationTime>2025-01-05T04:35:42.000000Z</creationTime>
          </creationInfo>
        </arrival>
        <arrival publicID="quakeml:service.scedc.caltech.edu/fdsnws/event/1/query?assocaro=266266781">
          <pickID>quakeml:service.scedc.caltech.edu/fdsnws/event/1/query?assocaro=266266781</pickID>
          <phase>S</phase>
          <timeCorrection>-0.37</timeCorrection>
          <azimuth>170.0</azimuth>
          <distance>0.5755</distance>
          <takeoffAngle>
            <value>94.0</value>
          </takeoffAngle>
          <timeResidual>0.61</timeResidual>
          <timeWeight>0.03</timeWeight>
          <creationInfo>
            <agencyID>CI</agencyID>
            <creationTime>2025-01-05T04:35:42.000000Z</creationTime>
          </creationInfo>
        </arrival>
        <arrival publicID="quakeml:service.scedc.caltech.edu/fdsnws/event/1/query?assocaro=266266789">
          <pickID>quakeml:service.scedc.caltech.edu/fdsnws/event/1/query?assocaro=266266789</pickID>
          <phase>S</phase>
          <timeCorrection>-0.26</timeCorrection>
          <azimuth>280.0</azimuth>
          <distance>0.5778</distance>
          <takeoffAngle>
            <value>94.0</value>
          </takeoffAngle>
          <timeResidual>-0.01</timeResidual>
          <timeWeight>0.03</timeWeight>
          <creationInfo>
            <agencyID>CI</agencyID>
            <creationTime>2025-01-05T04:35:42.000000Z</creationTime>
          </creationInfo>
        </arrival>
      </origin>
      <magnitude publicID="quakeml:service.scedc.caltech.edu/fdsnws/event/1/query?magnitudeid=109259621">
        <mag>
          <value>0.65</value>
          <uncertainty>0.264</uncertainty>
        </mag>
        <type>Ml</type>
        <originID>quakeml:service.scedc.caltech.edu/fdsnws/event/1/query?originid=105807397</originID>
        <methodID>smi:ci.anss.org/magnitude/CISNml2</methodID>
        <stationCount>13</stationCount>
        <azimuthalGap>97.4</azimuthalGap>
        <evaluationMode>automatic</evaluationMode>
        <evaluationStatus>preliminary</evaluationStatus>
        <stationMagnitudeContribution>
          <stationMagnitudeID>quakeml:service.scedc.caltech.edu/fdsnws/event/1/query?assocammid=929996989</stationMagnitudeID>
          <weight>1.0</weight>
          <residual>-0.13</residual>
        </stationMagnitudeContribution>
        <stationMagnitudeContribution>
          <stationMagnitudeID>quakeml:service.scedc.caltech.edu/fdsnws/event/1/query?assocammid=929997029</stationMagnitudeID>
          <weight>1.0</weight>
          <residual>-0.19</residual>
        </stationMagnitudeContribution>
        <stationMagnitudeContribution>
          <stationMagnitudeID>quakeml:service.scedc.caltech.edu/fdsnws/event/1/query?assocammid=929997013</stationMagnitudeID>
          <weight>1.0</weight>
          <residual>0.21</residual>
        </stationMagnitudeContribution>
        <stationMagnitudeContribution>
          <stationMagnitudeID>quakeml:service.scedc.caltech.edu/fdsnws/event/1/query?assocammid=929997045</stationMagnitudeID>
          <weight>1.0</weight>
          <residual>0.28</residual>
        </stationMagnitudeContribution>
        <stationMagnitudeContribution>
          <stationMagnitudeID>quakeml:service.scedc.caltech.edu/fdsnws/event/1/query?assocammid=929997037</stationMagnitudeID>
          <weight>1.0</weight>
          <residual>0.93</residual>
        </stationMagnitudeContribution>
        <stationMagnitudeContribution>
          <stationMagnitudeID>quakeml:service.scedc.caltech.edu/fdsnws/event/1/query?assocammid=929996949</stationMagnitudeID>
          <weight>1.0</weight>
          <residual>0.66</residual>
        </stationMagnitudeContribution>
        <stationMagnitudeContribution>
          <stationMagnitudeID>quakeml:service.scedc.caltech.edu/fdsnws/event/1/query?assocammid=929997005</stationMagnitudeID>
          <weight>1.0</weight>
          <residual>-0.04</residual>
        </stationMagnitudeContribution>
        <stationMagnitudeContribution>
          <stationMagnitudeID>quakeml:service.scedc.caltech.edu/fdsnws/event/1/query?assocammid=929996997</stationMagnitudeID>
          <weight>1.0</weight>
          <residual>-0.47</residual>
        </stationMagnitudeContribution>
        <stationMagnitudeContribution>
          <stationMagnitudeID>quakeml:service.scedc.caltech.edu/fdsnws/event/1/query?assocammid=929996981</stationMagnitudeID>
          <weight>1.0</weight>
          <residual>-0.35</residual>
        </stationMagnitudeContribution>
        <stationMagnitudeContribution>
          <stationMagnitudeID>quakeml:service.scedc.caltech.edu/fdsnws/event/1/query?assocammid=929996933</stationMagnitudeID>
          <weight>1.0</weight>
          <residual>-0.02</residual>
        </stationMagnitudeContribution>
        <stationMagnitudeContribution>
          <stationMagnitudeID>quakeml:service.scedc.caltech.edu/fdsnws/event/1/query?assocammid=929997021</stationMagnitudeID>
          <weight>1.0</weight>
          <residual>0.51</residual>
        </stationMagnitudeContribution>
        <stationMagnitudeContribution>
          <stationMagnitudeID>quakeml:service.scedc.caltech.edu/fdsnws/event/1/query?assocammid=929996909</stationMagnitudeID>
          <weight>1.0</weight>
          <residual>0.13</residual>
        </stationMagnitudeContribution>
        <stationMagnitudeContribution>
          <stationMagnitudeID>quakeml:service.scedc.caltech.edu/fdsnws/event/1/query?assocammid=929996901</stationMagnitudeID>
          <weight>1.0</weight>
          <residual>0.24</residual>
        </stationMagnitudeContribution>
        <stationMagnitudeContribution>
          <stationMagnitudeID>quakeml:service.scedc.caltech.edu/fdsnws/event/1/query?assocammid=929997053</stationMagnitudeID>
          <weight>1.0</weight>
          <residual>0.24</residual>
        </stationMagnitudeContribution>
        <stationMagnitudeContribution>
          <stationMagnitudeID>quakeml:service.scedc.caltech.edu/fdsnws/event/1/query?assocammid=929996973</stationMagnitudeID>
          <weight>1.0</weight>
          <residual>-0.35</residual>
        </stationMagnitudeContribution>
        <stationMagnitudeContribution>
          <stationMagnitudeID>quakeml:service.scedc.caltech.edu/fdsnws/event/1/query?assocammid=929996965</stationMagnitudeID>
          <weight>1.0</weight>
          <residual>-0.3</residual>
        </stationMagnitudeContribution>
        <stationMagnitudeContribution>
          <stationMagnitudeID>quakeml:service.scedc.caltech.edu/fdsnws/event/1/query?assocammid=929996917</stationMagnitudeID>
          <weight>1.0</weight>
          <residual>-0.24</residual>
        </stationMagnitudeContribution>
        <stationMagnitudeContribution>
          <stationMagnitudeID>quakeml:service.scedc.caltech.edu/fdsnws/event/1/query?assocammid=929996957</stationMagnitudeID>
          <weight>1.0</weight>
          <residual>-0.36</residual>
        </stationMagnitudeContribution>
        <stationMagnitudeContribution>
          <stationMagnitudeID>quakeml:service.scedc.caltech.edu/fdsnws/event/1/query?assocammid=929996925</stationMagnitudeID>
          <weight>1.0</weight>
          <residual>0.01</residual>
        </stationMagnitudeContribution>
        <stationMagnitudeContribution>
          <stationMagnitudeID>quakeml:service.scedc.caltech.edu/fdsnws/event/1/query?assocammid=929996941</stationMagnitudeID>
          <weight>1.0</weight>
          <residual>0.94</residual>
        </stationMagnitudeContribution>
        <creationInfo>
          <agencyID>CI</agencyID>
          <creationTime>2025-01-05T04:35:57.000000Z</creationTime>
        </creationInfo>
      </magnitude>
      <stationMagnitude publicID="quakeml:service.scedc.caltech.edu/fdsnws/event/1/query?assocammid=929996901">
        <originID>quakeml:service.scedc.caltech.edu/fdsnws/event/1/query?originid=105807397</originID>
        <mag>
          <value>0.89</value>
        </mag>
        <type>ML</type>
        <amplitudeID>quakeml:service.scedc.caltech.edu/fdsnws/event/1/query?ampid=929996901</amplitudeID>
        <waveformID networkCode="AZ" stationCode="KNW" locationCode="" channelCode="HHN"></waveformID>
      </stationMagnitude>
      <stationMagnitude publicID="quakeml:service.scedc.caltech.edu/fdsnws/event/1/query?assocammid=929996909">
        <originID>quakeml:service.scedc.caltech.edu/fdsnws/event/1/query?originid=105807397</originID>
        <mag>
          <value>0.78</value>
        </mag>
        <type>ML</type>
        <amplitudeID>quakeml:service.scedc.caltech.edu/fdsnws/event/1/query?ampid=929996909</amplitudeID>
        <waveformID networkCode="AZ" stationCode="KNW" locationCode="" channelCode="HHE"></waveformID>
      </stationMagnitude>
      <stationMagnitude publicID="quakeml:service.scedc.caltech.edu/fdsnws/event/1/query?assocammid=929996917">
        <originID>quakeml:service.scedc.caltech.edu/fdsnws/event/1/query?originid=105807397</originID>
        <mag>
          <value>0.41</value>
        </mag>
        <type>ML</type>
        <amplitudeID>quakeml:service.scedc.caltech.edu/fdsnws/event/1/query?ampid=929996917</amplitudeID>
        <waveformID networkCode="AZ" stationCode="CRY" locationCode="" channelCode="HHN"></waveformID>
      </stationMagnitude>
      <stationMagnitude publicID="quakeml:service.scedc.caltech.edu/fdsnws/event/1/query?assocammid=929996925">
        <originID>quakeml:service.scedc.caltech.edu/fdsnws/event/1/query?originid=105807397</originID>
        <mag>
          <value>0.66</value>
        </mag>
        <type>ML</type>
        <amplitudeID>quakeml:service.scedc.caltech.edu/fdsnws/event/1/query?ampid=929996925</amplitudeID>
        <waveformID networkCode="CI" stationCode="CSH" locationCode="" channelCode="HHN"></waveformID>
      </stationMagnitude>
      <stationMagnitude publicID="quakeml:service.scedc.caltech.edu/fdsnws/event/1/query?assocammid=929996933">
        <originID>quakeml:service.scedc.caltech.edu/fdsnws/event/1/query?originid=105807397</originID>
        <mag>
          <value>0.63</value>
        </mag>
        <type>ML</type>
        <amplitudeID>quakeml:service.scedc.caltech.edu/fdsnws/event/1/query?ampid=929996933</amplitudeID>
        <waveformID networkCode="CI" stationCode="CSH" locationCode="" channelCode="HHE"></waveformID>
      </stationMagnitude>
      <stationMagnitude publicID="quakeml:service.scedc.caltech.edu/fdsnws/event/1/query?assocammid=929996941">
        <originID>quakeml:service.scedc.caltech.edu/fdsnws/event/1/query?originid=105807397</originID>
        <mag>
          <value>1.59</value>
        </mag>
        <type>ML</type>
        <amplitudeID>quakeml:service.scedc.caltech.edu/fdsnws/event/1/query?ampid=929996941</amplitudeID>
        <waveformID networkCode="CI" stationCode="IDY" locationCode="" channelCode="HHN"></waveformID>
      </stationMagnitude>
      <stationMagnitude publicID="quakeml:service.scedc.caltech.edu/fdsnws/event/1/query?assocammid=929996949">
        <originID>quakeml:service.scedc.caltech.edu/fdsnws/event/1/query?originid=105807397</originID>
        <mag>
          <value>1.31</value>
        </mag>
        <type>ML</type>
        <amplitudeID>quakeml:service.scedc.caltech.edu/fdsnws/event/1/query?ampid=929996949</amplitudeID>
        <waveformID networkCode="CI" stationCode="IDY" locationCode="" channelCode="HHE"></waveformID>
      </stationMagnitude>
      <stationMagnitude publicID="quakeml:service.scedc.caltech.edu/fdsnws/event/1/query?assocammid=929996957">
        <originID>quakeml:service.scedc.caltech.edu/fdsnws/event/1/query?originid=105807397</originID>
        <mag>
          <value>0.29</value>
        </mag>
        <type>ML</type>
        <amplitudeID>quakeml:service.scedc.caltech.edu/fdsnws/event/1/query?ampid=929996957</amplitudeID>
        <waveformID networkCode="CI" stationCode="DNR" locationCode="" channelCode="HHN"></waveformID>
      </stationMagnitude>
      <stationMagnitude publicID="quakeml:service.scedc.caltech.edu/fdsnws/event/1/query?assocammid=929996965">
        <originID>quakeml:service.scedc.caltech.edu/fdsnws/event/1/query?originid=105807397</originID>
        <mag>
          <value>0.35</value>
        </mag>
        <type>ML</type>
        <amplitudeID>quakeml:service.scedc.caltech.edu/fdsnws/event/1/query?ampid=929996965</amplitudeID>
        <waveformID networkCode="CI" stationCode="DNR" locationCode="" channelCode="HHE"></waveformID>
      </stationMagnitude>
      <stationMagnitude publicID="quakeml:service.scedc.caltech.edu/fdsnws/event/1/query?assocammid=929996973">
        <originID>quakeml:service.scedc.caltech.edu/fdsnws/event/1/query?originid=105807397</originID>
        <mag>
          <value>0.3</value>
        </mag>
        <type>ML</type>
        <amplitudeID>quakeml:service.scedc.caltech.edu/fdsnws/event/1/query?ampid=929996973</amplitudeID>
        <waveformID networkCode="AZ" stationCode="RDM" locationCode="" channelCode="HHN"></waveformID>
      </stationMagnitude>
      <stationMagnitude publicID="quakeml:service.scedc.caltech.edu/fdsnws/event/1/query?assocammid=929996981">
        <originID>quakeml:service.scedc.caltech.edu/fdsnws/event/1/query?originid=105807397</originID>
        <mag>
          <value>0.3</value>
        </mag>
        <type>ML</type>
        <amplitudeID>quakeml:service.scedc.caltech.edu/fdsnws/event/1/query?ampid=929996981</amplitudeID>
        <waveformID networkCode="AZ" stationCode="RDM" locationCode="" channelCode="HHE"></waveformID>
      </stationMagnitude>
      <stationMagnitude publicID="quakeml:service.scedc.caltech.edu/fdsnws/event/1/query?assocammid=929996989">
        <originID>quakeml:service.scedc.caltech.edu/fdsnws/event/1/query?originid=105807397</originID>
        <mag>
          <value>0.52</value>
        </mag>
        <type>ML</type>
        <amplitudeID>quakeml:service.scedc.caltech.edu/fdsnws/event/1/query?ampid=929996989</amplitudeID>
        <waveformID networkCode="AZ" stationCode="SND" locationCode="" channelCode="HHN"></waveformID>
      </stationMagnitude>
      <stationMagnitude publicID="quakeml:service.scedc.caltech.edu/fdsnws/event/1/query?assocammid=929996997">
        <originID>quakeml:service.scedc.caltech.edu/fdsnws/event/1/query?originid=105807397</originID>
        <mag>
          <value>0.18</value>
        </mag>
        <type>ML</type>
        <amplitudeID>quakeml:service.scedc.caltech.edu/fdsnws/event/1/query?ampid=929996997</amplitudeID>
        <waveformID networkCode="CI" stationCode="SLR" locationCode="" channelCode="HHN"></waveformID>
      </stationMagnitude>
      <stationMagnitude publicID="quakeml:service.scedc.caltech.edu/fdsnws/event/1/query?assocammid=929997005">
        <originID>quakeml:service.scedc.caltech.edu/fdsnws/event/1/query?originid=105807397</originID>
        <mag>
          <value>0.61</value>
        </mag>
        <type>ML</type>
        <amplitudeID>quakeml:service.scedc.caltech.edu/fdsnws/event/1/query?ampid=929997005</amplitudeID>
        <waveformID networkCode="CI" stationCode="HMT2" locationCode="" channelCode="HHN"></waveformID>
      </stationMagnitude>
      <stationMagnitude publicID="quakeml:service.scedc.caltech.edu/fdsnws/event/1/query?assocammid=929997013">
        <originID>quakeml:service.scedc.caltech.edu/fdsnws/event/1/query?originid=105807397</originID>
        <mag>
          <value>0.86</value>
        </mag>
        <type>ML</type>
        <amplitudeID>quakeml:service.scedc.caltech.edu/fdsnws/event/1/query?ampid=929997013</amplitudeID>
        <waveformID networkCode="CI" stationCode="HMT2" locationCode="" channelCode="HHE"></waveformID>
      </stationMagnitude>
      <stationMagnitude publicID="quakeml:service.scedc.caltech.edu/fdsnws/event/1/query?assocammid=929997021">
        <originID>quakeml:service.scedc.caltech.edu/fdsnws/event/1/query?originid=105807397</originID>
        <mag>
          <value>1.16</value>
        </mag>
        <type>ML</type>
        <amplitudeID>quakeml:service.scedc.caltech.edu/fdsnws/event/1/query?ampid=929997021</amplitudeID>
        <waveformID networkCode="CI" stationCode="MSJ" locationCode="" channelCode="HHN"></waveformID>
      </stationMagnitude>
      <stationMagnitude publicID="quakeml:service.scedc.caltech.edu/fdsnws/event/1/query?assocammid=929997029">
        <originID>quakeml:service.scedc.caltech.edu/fdsnws/event/1/query?originid=105807397</originID>
        <mag>
          <value>0.46</value>
        </mag>
        <type>ML</type>
        <amplitudeID>quakeml:service.scedc.caltech.edu/fdsnws/event/1/query?ampid=929997029</amplitudeID>
        <waveformID networkCode="CI" stationCode="PLM" locationCode="" channelCode="HHE"></waveformID>
      </stationMagnitude>
      <stationMagnitude publicID="quakeml:service.scedc.caltech.edu/fdsnws/event/1/query?assocammid=929997037">
        <originID>quakeml:service.scedc.caltech.edu/fdsnws/event/1/query?originid=105807397</originID>
        <mag>
          <value>1.58</value>
        </mag>
        <type>ML</type>
        <amplitudeID>quakeml:service.scedc.caltech.edu/fdsnws/event/1/query?ampid=929997037</amplitudeID>
        <waveformID networkCode="CI" stationCode="BBS" locationCode="" channelCode="HHN"></waveformID>
      </stationMagnitude>
      <stationMagnitude publicID="quakeml:service.scedc.caltech.edu/fdsnws/event/1/query?assocammid=929997045">
        <originID>quakeml:service.scedc.caltech.edu/fdsnws/event/1/query?originid=105807397</originID>
        <mag>
          <value>0.93</value>
        </mag>
        <type>ML</type>
        <amplitudeID>quakeml:service.scedc.caltech.edu/fdsnws/event/1/query?ampid=929997045</amplitudeID>
        <waveformID networkCode="CI" stationCode="VLY" locationCode="" channelCode="HHN"></waveformID>
      </stationMagnitude>
      <stationMagnitude publicID="quakeml:service.scedc.caltech.edu/fdsnws/event/1/query?assocammid=929997053">
        <originID>quakeml:service.scedc.caltech.edu/fdsnws/event/1/query?originid=105807397</originID>
        <mag>
          <value>0.89</value>
        </mag>
        <type>ML</type>
        <amplitudeID>quakeml:service.scedc.caltech.edu/fdsnws/event/1/query?ampid=929997053</amplitudeID>
        <waveformID networkCode="CI" stationCode="VLY" locationCode="" channelCode="HHE"></waveformID>
      </stationMagnitude>
      <pick publicID="quakeml:service.scedc.caltech.edu/fdsnws/event/1/query?assocaro=144511383">
        <time>
          <value>2025-01-05T04:31:31.380000Z</value>
          <uncertainty>0.15</uncertainty>
        </time>
        <waveformID networkCode="AZ" stationCode="FRD" locationCode="" channelCode="HHZ"></waveformID>
        <phaseHint>P</phaseHint>
        <polarity>undecidable</polarity>
        <evaluationMode>automatic</evaluationMode>
        <evaluationStatus>preliminary</evaluationStatus>
        <creationInfo>
          <agencyID>CI</agencyID>
          <creationTime>2025-01-05T04:32:37.000000Z</creationTime>
        </creationInfo>
      </pick>
      <pick publicID="quakeml:service.scedc.caltech.edu/fdsnws/event/1/query?assocaro=144511431">
        <time>
          <value>2025-01-05T04:31:41.040000Z</value>
          <uncertainty>0.15</uncertainty>
        </time>
        <waveformID networkCode="AZ" stationCode="SMER" locationCode="" channelCode="HHE"></waveformID>
        <phaseHint>S</phaseHint>
        <polarity>undecidable</polarity>
        <evaluationMode>automatic</evaluationMode>
        <evaluationStatus>preliminary</evaluationStatus>
        <creationInfo>
          <agencyID>CI</agencyID>
          <creationTime>2025-01-05T04:32:37.000000Z</creationTime>
        </creationInfo>
      </pick>
      <pick publicID="quakeml:service.scedc.caltech.edu/fdsnws/event/1/query?assocaro=144511543">
        <time>
          <value>2025-01-05T04:31:34.540000Z</value>
          <uncertainty>0.03</uncertainty>
        </time>
        <waveformID networkCode="CI" stationCode="POB2" locationCode="" channelCode="HHE"></waveformID>
        <phaseHint>S</phaseHint>
        <polarity>undecidable</polarity>
        <evaluationMode>automatic</evaluationMode>
        <evaluationStatus>preliminary</evaluationStatus>
        <creationInfo>
          <agencyID>CI</agencyID>
          <creationTime>2025-01-05T04:32:37.000000Z</creationTime>
        </creationInfo>
      </pick>
      <pick publicID="quakeml:service.scedc.caltech.edu/fdsnws/event/1/query?assocaro=266266501">
        <time>
          <value>2025-01-05T04:31:29.900000Z</value>
          <uncertainty>0.03</uncertainty>
        </time>
        <waveformID networkCode="AZ" stationCode="KNW" locationCode="" channelCode="HHZ"></waveformID>
        <onset>impulsive</onset>
        <phaseHint>P</phaseHint>
        <polarity>negative</polarity>
        <evaluationMode>automatic</evaluationMode>
        <evaluationStatus>preliminary</evaluationStatus>
        <creationInfo>
          <agencyID>CI</agencyID>
          <creationTime>2025-01-05T04:35:42.000000Z</creationTime>
        </creationInfo>
      </pick>
      <pick publicID="quakeml:service.scedc.caltech.edu/fdsnws/event/1/query?assocaro=266266509">
        <time>
          <value>2025-01-05T04:31:32.080000Z</value>
          <uncertainty>0.06</uncertainty>
        </time>
        <waveformID networkCode="AZ" stationCode="KNW" locationCode="" channelCode="HHE"></waveformID>
        <onset>impulsive</onset>
        <phaseHint>S</phaseHint>
        <polarity>undecidable</polarity>
        <evaluationMode>automatic</evaluationMode>
        <evaluationStatus>preliminary</evaluationStatus>
        <creationInfo>
          <agencyID>CI</agencyID>
          <creationTime>2025-01-05T04:35:42.000000Z</creationTime>
        </creationInfo>
      </pick>
      <pick publicID="quakeml:service.scedc.caltech.edu/fdsnws/event/1/query?assocaro=266266517">
        <time>
          <value>2025-01-05T04:31:30.160000Z</value>
          <uncertainty>0.06</uncertainty>
        </time>
        <waveformID networkCode="AZ" stationCode="CRY" locationCode="" channelCode="HHZ"></waveformID>
        <onset>impulsive</onset>
        <phaseHint>P</phaseHint>
        <polarity>positive</polarity>
        <evaluationMode>automatic</evaluationMode>
        <evaluationStatus>preliminary</evaluationStatus>
        <creationInfo>
          <agencyID>CI</agencyID>
          <creationTime>2025-01-05T04:35:42.000000Z</creationTime>
        </creationInfo>
      </pick>
      <pick publicID="quakeml:service.scedc.caltech.edu/fdsnws/event/1/query?assocaro=266266525">
        <time>
          <value>2025-01-05T04:31:32.620000Z</value>
          <uncertainty>0.15</uncertainty>
        </time>
        <waveformID networkCode="AZ" stationCode="CRY" locationCode="" channelCode="HHE"></waveformID>
        <onset>emergent</onset>
        <phaseHint>S</phaseHint>
        <polarity>undecidable</polarity>
        <evaluationMode>automatic</evaluationMode>
        <evaluationStatus>preliminary</evaluationStatus>
        <creationInfo>
          <agencyID>CI</agencyID>
          <creationTime>2025-01-05T04:35:42.000000Z</creationTime>
        </creationInfo>
      </pick>
      <pick publicID="quakeml:service.scedc.caltech.edu/fdsnws/event/1/query?assocaro=266266533">
        <time>
          <value>2025-01-05T04:31:30.180000Z</value>
          <uncertainty>0.03</uncertainty>
        </time>
        <waveformID networkCode="CI" stationCode="CSH" locationCode="" channelCode="HHZ"></waveformID>
        <onset>impulsive</onset>
        <phaseHint>P</phaseHint>
        <polarity>positive</polarity>
        <evaluationMode>automatic</evaluationMode>
        <evaluationStatus>preliminary</evaluationStatus>
        <creationInfo>
          <agencyID>CI</agencyID>
          <creationTime>2025-01-05T04:35:42.000000Z</creationTime>
        </creationInfo>
      </pick>
      <pick publicID="quakeml:service.scedc.caltech.edu/fdsnws/event/1/query?assocaro=266266541">
        <time>
          <value>2025-01-05T04:31:32.620000Z</value>
          <uncertainty>0.15</uncertainty>
        </time>
        <waveformID networkCode="CI" stationCode="CSH" locationCode="" channelCode="HHE"></waveformID>
        <onset>emergent</onset>
        <phaseHint>S</phaseHint>
        <polarity>undecidable</polarity>
        <evaluationMode>automatic</evaluationMode>
        <evaluationStatus>preliminary</evaluationStatus>
        <creationInfo>
          <agencyID>CI</agencyID>
          <creationTime>2025-01-05T04:35:42.000000Z</creationTime>
        </creationInfo>
      </pick>
      <pick publicID="quakeml:service.scedc.caltech.edu/fdsnws/event/1/query?assocaro=266266549">
        <time>
          <value>2025-01-05T04:31:30.600000Z</value>
          <uncertainty>0.15</uncertainty>
        </time>
        <waveformID networkCode="CI" stationCode="IDY" locationCode="" channelCode="HHZ"></waveformID>
        <onset>emergent</onset>
        <phaseHint>P</phaseHint>
        <polarity>undecidable</polarity>
        <evaluationMode>automatic</evaluationMode>
        <evaluationStatus>preliminary</evaluationStatus>
        <creationInfo>
          <agencyID>CI</agencyID>
          <creationTime>2025-01-05T04:35:42.000000Z</creationTime>
        </creationInfo>
      </pick>
      <pick publicID="quakeml:service.scedc.caltech.edu/fdsnws/event/1/query?assocaro=266266557">
        <time>
          <value>2025-01-05T04:31:30.550000Z</value>
          <uncertainty>0.06</uncertainty>
        </time>
        <waveformID networkCode="CI" stationCode="DNR" locationCode="" channelCode="HHZ"></waveformID>
        <onset>impulsive</onset>
        <phaseHint>P</phaseHint>
        <polarity>undecidable</polarity>
        <evaluationMode>automatic</evaluationMode>
        <evaluationStatus>preliminary</evaluationStatus>
        <creationInfo>
          <agencyID>CI</agencyID>
          <creationTime>2025-01-05T04:35:42.000000Z</creationTime>
        </creationInfo>
      </pick>
      <pick publicID="quakeml:service.scedc.caltech.edu/fdsnws/event/1/query?assocaro=266266565">
        <time>
          <value>2025-01-05T04:31:33.520000Z</value>
          <uncertainty>0.15</uncertainty>
        </time>
        <waveformID networkCode="CI" stationCode="DNR" locationCode="" channelCode="HHE"></waveformID>
        <onset>emergent</onset>
        <phaseHint>S</phaseHint>
        <polarity>undecidable</polarity>
        <evaluationMode>automatic</evaluationMode>
        <evaluationStatus>preliminary</evaluationStatus>
        <creationInfo>
          <agencyID>CI</agencyID>
          <creationTime>2025-01-05T04:35:42.000000Z</creationTime>
        </creationInfo>
      </pick>
      <pick publicID="quakeml:service.scedc.caltech.edu/fdsnws/event/1/query?assocaro=266266573">
        <time>
          <value>2025-01-05T04:31:30.420000Z</value>
          <uncertainty>0.15</uncertainty>
        </time>
        <waveformID networkCode="AZ" stationCode="RDM" locationCode="" channelCode="HHZ"></waveformID>
        <onset>emergent</onset>
        <phaseHint>P</phaseHint>
        <polarity>undecidable</polarity>
        <evaluationMode>automatic</evaluationMode>
        <evaluationStatus>preliminary</evaluationStatus>
        <creationInfo>
          <agencyID>CI</agencyID>
          <creationTime>2025-01-05T04:35:42.000000Z</creationTime>
        </creationInfo>
      </pick>
      <pick publicID="quakeml:service.scedc.caltech.edu/fdsnws/event/1/query?assocaro=266266581">
        <time>
          <value>2025-01-05T04:31:33.010000Z</value>
          <uncertainty>0.15</uncertainty>
        </time>
        <waveformID networkCode="AZ" stationCode="RDM" locationCode="" channelCode="HHE"></waveformID>
        <onset>emergent</onset>
        <phaseHint>S</phaseHint>
        <polarity>undecidable</polarity>
        <evaluationMode>automatic</evaluationMode>
        <evaluationStatus>preliminary</evaluationStatus>
        <creationInfo>
          <agencyID>CI</agencyID>
          <creationTime>2025-01-05T04:35:42.000000Z</creationTime>
        </creationInfo>
      </pick>
      <pick publicID="quakeml:service.scedc.caltech.edu/fdsnws/event/1/query?assocaro=266266589">
        <time>
          <value>2025-01-05T04:31:31.080000Z</value>
          <uncertainty>0.03</uncertainty>
        </time>
        <waveformID networkCode="CI" stationCode="ANG" locationCode="" channelCode="HHZ"></waveformID>
        <onset>impulsive</onset>
        <phaseHint>P</phaseHint>
        <polarity>undecidable</polarity>
        <evaluationMode>automatic</evaluationMode>
        <evaluationStatus>preliminary</evaluationStatus>
        <creationInfo>
          <agencyID>CI</agencyID>
          <creationTime>2025-01-05T04:35:42.000000Z</creationTime>
        </creationInfo>
      </pick>
      <pick publicID="quakeml:service.scedc.caltech.edu/fdsnws/event/1/query?assocaro=266266597">
        <time>
          <value>2025-01-05T04:31:34.070000Z</value>
          <uncertainty>0.15</uncertainty>
        </time>
        <waveformID networkCode="CI" stationCode="ANG" locationCode="" channelCode="HHE"></waveformID>
        <onset>emergent</onset>
        <phaseHint>S</phaseHint>
        <polarity>undecidable</polarity>
        <evaluationMode>automatic</evaluationMode>
        <evaluationStatus>preliminary</evaluationStatus>
        <creationInfo>
          <agencyID>CI</agencyID>
          <creationTime>2025-01-05T04:35:42.000000Z</creationTime>
        </creationInfo>
      </pick>
      <pick publicID="quakeml:service.scedc.caltech.edu/fdsnws/event/1/query?assocaro=266266605">
        <time>
          <value>2025-01-05T04:31:31.470000Z</value>
          <uncertainty>0.15</uncertainty>
        </time>
        <waveformID networkCode="CI" stationCode="SLR" locationCode="" channelCode="BHZ"></waveformID>
        <onset>emergent</onset>
        <phaseHint>P</phaseHint>
        <polarity>undecidable</polarity>
        <evaluationMode>automatic</evaluationMode>
        <evaluationStatus>preliminary</evaluationStatus>
        <creationInfo>
          <agencyID>CI</agencyID>
          <creationTime>2025-01-05T04:35:42.000000Z</creationTime>
        </creationInfo>
      </pick>
      <pick publicID="quakeml:service.scedc.caltech.edu/fdsnws/event/1/query?assocaro=266266613">
        <time>
          <value>2025-01-05T04:31:34.930000Z</value>
          <uncertainty>0.15</uncertainty>
        </time>
        <waveformID networkCode="CI" stationCode="SLR" locationCode="" channelCode="BHE"></waveformID>
        <onset>emergent</onset>
        <phaseHint>S</phaseHint>
        <polarity>undecidable</polarity>
        <evaluationMode>automatic</evaluationMode>
        <evaluationStatus>preliminary</evaluationStatus>
        <creationInfo>
          <agencyID>CI</agencyID>
          <creationTime>2025-01-05T04:35:42.000000Z</creationTime>
        </creationInfo>
      </pick>
      <pick publicID="quakeml:service.scedc.caltech.edu/fdsnws/event/1/query?assocaro=266266621">
        <time>
          <value>2025-01-05T04:31:32.310000Z</value>
          <uncertainty>0.15</uncertainty>
        </time>
        <waveformID networkCode="CI" stationCode="HMT2" locationCode="" channelCode="HHZ"></waveformID>
        <onset>emergent</onset>
        <phaseHint>P</phaseHint>
        <polarity>undecidable</polarity>
        <evaluationMode>automatic</evaluationMode>
        <evaluationStatus>preliminary</evaluationStatus>
        <creationInfo>
          <agencyID>CI</agencyID>
          <creationTime>2025-01-05T04:35:42.000000Z</creationTime>
        </creationInfo>
      </pick>
      <pick publicID="quakeml:service.scedc.caltech.edu/fdsnws/event/1/query?assocaro=266266629">
        <time>
          <value>2025-01-05T04:31:36.300000Z</value>
          <uncertainty>0.15</uncertainty>
        </time>
        <waveformID networkCode="CI" stationCode="HMT2" locationCode="" channelCode="HHE"></waveformID>
        <onset>emergent</onset>
        <phaseHint>S</phaseHint>
        <polarity>undecidable</polarity>
        <evaluationMode>automatic</evaluationMode>
        <evaluationStatus>preliminary</evaluationStatus>
        <creationInfo>
          <agencyID>CI</agencyID>
          <creationTime>2025-01-05T04:35:42.000000Z</creationTime>
        </creationInfo>
      </pick>
      <pick publicID="quakeml:service.scedc.caltech.edu/fdsnws/event/1/query?assocaro=266266637">
        <time>
          <value>2025-01-05T04:31:32.200000Z</value>
          <uncertainty>0.06</uncertainty>
        </time>
        <waveformID networkCode="CI" stationCode="DGR" locationCode="" channelCode="HHZ"></waveformID>
        <onset>impulsive</onset>
        <phaseHint>P</phaseHint>
        <polarity>undecidable</polarity>
        <evaluationMode>automatic</evaluationMode>
        <evaluationStatus>preliminary</evaluationStatus>
        <creationInfo>
          <agencyID>CI</agencyID>
          <creationTime>2025-01-05T04:35:42.000000Z</creationTime>
        </creationInfo>
      </pick>
      <pick publicID="quakeml:service.scedc.caltech.edu/fdsnws/event/1/query?assocaro=266266645">
        <time>
          <value>2025-01-05T04:31:35.980000Z</value>
          <uncertainty>0.15</uncertainty>
        </time>
        <waveformID networkCode="CI" stationCode="DGR" locationCode="" channelCode="HHE"></waveformID>
        <onset>emergent</onset>
        <phaseHint>S</phaseHint>
        <polarity>undecidable</polarity>
        <evaluationMode>automatic</evaluationMode>
        <evaluationStatus>preliminary</evaluationStatus>
        <creationInfo>
          <agencyID>CI</agencyID>
          <creationTime>2025-01-05T04:35:42.000000Z</creationTime>
        </creationInfo>
      </pick>
      <pick publicID="quakeml:service.scedc.caltech.edu/fdsnws/event/1/query?assocaro=266266653">
        <time>
          <value>2025-01-05T04:31:32.490000Z</value>
          <uncertainty>0.03</uncertainty>
        </time>
        <waveformID networkCode="CI" stationCode="PMD" locationCode="" channelCode="HHZ"></waveformID>
        <onset>impulsive</onset>
        <phaseHint>P</phaseHint>
        <polarity>undecidable</polarity>
        <evaluationMode>automatic</evaluationMode>
        <evaluationStatus>preliminary</evaluationStatus>
        <creationInfo>
          <agencyID>CI</agencyID>
          <creationTime>2025-01-05T04:35:42.000000Z</creationTime>
        </creationInfo>
      </pick>
      <pick publicID="quakeml:service.scedc.caltech.edu/fdsnws/event/1/query?assocaro=266266661">
        <time>
          <value>2025-01-05T04:31:36.520000Z</value>
          <uncertainty>0.15</uncertainty>
        </time>
        <waveformID networkCode="CI" stationCode="PMD" locationCode="" channelCode="HHE"></waveformID>
        <onset>emergent</onset>
        <phaseHint>S</phaseHint>
        <polarity>undecidable</polarity>
        <evaluationMode>automatic</evaluationMode>
        <evaluationStatus>preliminary</evaluationStatus>
        <creationInfo>
          <agencyID>CI</agencyID>
          <creationTime>2025-01-05T04:35:42.000000Z</creationTime>
        </creationInfo>
      </pick>
      <pick publicID="quakeml:service.scedc.caltech.edu/fdsnws/event/1/query?assocaro=266266669">
        <time>
          <value>2025-01-05T04:31:32.630000Z</value>
          <uncertainty>0.15</uncertainty>
        </time>
        <waveformID networkCode="CI" stationCode="BAC" locationCode="" channelCode="EHZ"></waveformID>
        <onset>emergent</onset>
        <phaseHint>P</phaseHint>
        <polarity>undecidable</polarity>
        <evaluationMode>automatic</evaluationMode>
        <evaluationStatus>preliminary</evaluationStatus>
        <creationInfo>
          <agencyID>CI</agencyID>
          <creationTime>2025-01-05T04:35:42.000000Z</creationTime>
        </creationInfo>
      </pick>
      <pick publicID="quakeml:service.scedc.caltech.edu/fdsnws/event/1/query?assocaro=266266677">
        <time>
          <value>2025-01-05T04:31:33.580000Z</value>
          <uncertainty>0.03</uncertainty>
        </time>
        <waveformID networkCode="AZ" stationCode="LVA2" locationCode="" channelCode="HHZ"></waveformID>
        <onset>impulsive</onset>
        <phaseHint>P</phaseHint>
        <polarity>negative</polarity>
        <evaluationMode>automatic</evaluationMode>
        <evaluationStatus>preliminary</evaluationStatus>
        <creationInfo>
          <agencyID>CI</agencyID>
          <creationTime>2025-01-05T04:35:42.000000Z</creationTime>
        </creationInfo>
      </pick>
      <pick publicID="quakeml:service.scedc.caltech.edu/fdsnws/event/1/query?assocaro=266266685">
        <time>
          <value>2025-01-05T04:31:38.360000Z</value>
          <uncertainty>0.15</uncertainty>
        </time>
        <waveformID networkCode="AZ" stationCode="LVA2" locationCode="" channelCode="HHE"></waveformID>
        <onset>emergent</onset>
        <phaseHint>S</phaseHint>
        <polarity>undecidable</polarity>
        <evaluationMode>automatic</evaluationMode>
        <evaluationStatus>preliminary</evaluationStatus>
        <creationInfo>
          <agencyID>CI</agencyID>
          <creationTime>2025-01-05T04:35:42.000000Z</creationTime>
        </creationInfo>
      </pick>
      <pick publicID="quakeml:service.scedc.caltech.edu/fdsnws/event/1/query?assocaro=266266693">
        <time>
          <value>2025-01-05T04:31:33.460000Z</value>
          <uncertainty>0.15</uncertainty>
        </time>
        <waveformID networkCode="CI" stationCode="PLM" locationCode="" channelCode="HHZ"></waveformID>
        <onset>emergent</onset>
        <phaseHint>P</phaseHint>
        <polarity>undecidable</polarity>
        <evaluationMode>automatic</evaluationMode>
        <evaluationStatus>preliminary</evaluationStatus>
        <creationInfo>
          <agencyID>CI</agencyID>
          <creationTime>2025-01-05T04:35:42.000000Z</creationTime>
        </creationInfo>
      </pick>
      <pick publicID="quakeml:service.scedc.caltech.edu/fdsnws/event/1/query?assocaro=266266701">
        <time>
          <value>2025-01-05T04:31:38.280000Z</value>
          <uncertainty>0.15</uncertainty>
        </time>
        <waveformID networkCode="CI" stationCode="PLM" locationCode="" channelCode="HHE"></waveformID>
        <onset>emergent</onset>
        <phaseHint>S</phaseHint>
        <polarity>undecidable</polarity>
        <evaluationMode>automatic</evaluationMode>
        <evaluationStatus>preliminary</evaluationStatus>
        <creationInfo>
          <agencyID>CI</agencyID>
          <creationTime>2025-01-05T04:35:42.000000Z</creationTime>
        </creationInfo>
      </pick>
      <pick publicID="quakeml:service.scedc.caltech.edu/fdsnws/event/1/query?assocaro=266266709">
        <time>
          <value>2025-01-05T04:31:40.350000Z</value>
          <uncertainty>0.3</uncertainty>
        </time>
        <waveformID networkCode="CI" stationCode="PALA" locationCode="" channelCode="BHE"></waveformID>
        <onset>emergent</onset>
        <phaseHint>S</phaseHint>
        <polarity>undecidable</polarity>
        <evaluationMode>automatic</evaluationMode>
        <evaluationStatus>preliminary</evaluationStatus>
        <creationInfo>
          <agencyID>CI</agencyID>
          <creationTime>2025-01-05T04:35:42.000000Z</creationTime>
        </creationInfo>
      </pick>
      <pick publicID="quakeml:service.scedc.caltech.edu/fdsnws/event/1/query?assocaro=266266717">
        <time>
          <value>2025-01-05T04:31:34.710000Z</value>
          <uncertainty>0.15</uncertainty>
        </time>
        <waveformID networkCode="CI" stationCode="MSC" locationCode="" channelCode="HHZ"></waveformID>
        <onset>emergent</onset>
        <phaseHint>P</phaseHint>
        <polarity>undecidable</polarity>
        <evaluationMode>automatic</evaluationMode>
        <evaluationStatus>preliminary</evaluationStatus>
        <creationInfo>
          <agencyID>CI</agencyID>
          <creationTime>2025-01-05T04:35:42.000000Z</creationTime>
        </creationInfo>
      </pick>
      <pick publicID="quakeml:service.scedc.caltech.edu/fdsnws/event/1/query?assocaro=266266725">
        <time>
          <value>2025-01-05T04:31:40.580000Z</value>
          <uncertainty>0.3</uncertainty>
        </time>
        <waveformID networkCode="CI" stationCode="MSC" locationCode="" channelCode="HHE"></waveformID>
        <onset>emergent</onset>
        <phaseHint>S</phaseHint>
        <polarity>undecidable</polarity>
        <evaluationMode>automatic</evaluationMode>
        <evaluationStatus>preliminary</evaluationStatus>
        <creationInfo>
          <agencyID>CI</agencyID>
          <creationTime>2025-01-05T04:35:42.000000Z</creationTime>
        </creationInfo>
      </pick>
      <pick publicID="quakeml:service.scedc.caltech.edu/fdsnws/event/1/query?assocaro=266266733">
        <time>
          <value>2025-01-05T04:31:34.970000Z</value>
          <uncertainty>0.15</uncertainty>
        </time>
        <waveformID networkCode="CI" stationCode="LKH" locationCode="" channelCode="HHZ"></waveformID>
        <onset>emergent</onset>
        <phaseHint>P</phaseHint>
        <polarity>undecidable</polarity>
        <evaluationMode>automatic</evaluationMode>
        <evaluationStatus>preliminary</evaluationStatus>
        <creationInfo>
          <agencyID>CI</agencyID>
          <creationTime>2025-01-05T04:35:42.000000Z</creationTime>
        </creationInfo>
      </pick>
      <pick publicID="quakeml:service.scedc.caltech.edu/fdsnws/event/1/query?assocaro=266266741">
        <time>
          <value>2025-01-05T04:31:41.580000Z</value>
          <uncertainty>0.3</uncertainty>
        </time>
        <waveformID networkCode="CI" stationCode="RCR" locationCode="" channelCode="HHE"></waveformID>
        <onset>emergent</onset>
        <phaseHint>S</phaseHint>
        <polarity>undecidable</polarity>
        <evaluationMode>automatic</evaluationMode>
        <evaluationStatus>preliminary</evaluationStatus>
        <creationInfo>
          <agencyID>CI</agencyID>
          <creationTime>2025-01-05T04:35:42.000000Z</creationTime>
        </creationInfo>
      </pick>
      <pick publicID="quakeml:service.scedc.caltech.edu/fdsnws/event/1/query?assocaro=266266749">
        <time>
          <value>2025-01-05T04:31:35.660000Z</value>
          <uncertainty>0.15</uncertainty>
        </time>
        <waveformID networkCode="CI" stationCode="MTG" locationCode="" channelCode="BHZ"></waveformID>
        <onset>emergent</onset>
        <phaseHint>P</phaseHint>
        <polarity>undecidable</polarity>
        <evaluationMode>automatic</evaluationMode>
        <evaluationStatus>preliminary</evaluationStatus>
        <creationInfo>
          <agencyID>CI</agencyID>
          <creationTime>2025-01-05T04:35:42.000000Z</creationTime>
        </creationInfo>
      </pick>
      <pick publicID="quakeml:service.scedc.caltech.edu/fdsnws/event/1/query?assocaro=266266757">
        <time>
          <value>2025-01-05T04:31:42.090000Z</value>
          <uncertainty>0.15</uncertainty>
        </time>
        <waveformID networkCode="CI" stationCode="MTG" locationCode="" channelCode="HHE"></waveformID>
        <onset>emergent</onset>
        <phaseHint>S</phaseHint>
        <polarity>undecidable</polarity>
        <evaluationMode>automatic</evaluationMode>
        <evaluationStatus>preliminary</evaluationStatus>
        <creationInfo>
          <agencyID>CI</agencyID>
          <creationTime>2025-01-05T04:35:42.000000Z</creationTime>
        </creationInfo>
      </pick>
      <pick publicID="quakeml:service.scedc.caltech.edu/fdsnws/event/1/query?assocaro=266266765">
        <time>
          <value>2025-01-05T04:31:37.470000Z</value>
          <uncertainty>0.3</uncertainty>
        </time>
        <waveformID networkCode="CI" stationCode="BLA2" locationCode="" channelCode="HHZ"></waveformID>
        <onset>emergent</onset>
        <phaseHint>P</phaseHint>
        <polarity>undecidable</polarity>
        <evaluationMode>automatic</evaluationMode>
        <evaluationStatus>preliminary</evaluationStatus>
        <creationInfo>
          <agencyID>CI</agencyID>
          <creationTime>2025-01-05T04:35:42.000000Z</creationTime>
        </creationInfo>
      </pick>
      <pick publicID="quakeml:service.scedc.caltech.edu/fdsnws/event/1/query?assocaro=266266773">
        <time>
          <value>2025-01-05T04:31:43.590000Z</value>
          <uncertainty>0.3</uncertainty>
        </time>
        <waveformID networkCode="CI" stationCode="BLA2" locationCode="" channelCode="HHE"></waveformID>
        <onset>emergent</onset>
        <phaseHint>S</phaseHint>
        <polarity>undecidable</polarity>
        <evaluationMode>automatic</evaluationMode>
        <evaluationStatus>preliminary</evaluationStatus>
        <creationInfo>
          <agencyID>CI</agencyID>
          <creationTime>2025-01-05T04:35:42.000000Z</creationTime>
        </creationInfo>
      </pick>
      <pick publicID="quakeml:service.scedc.caltech.edu/fdsnws/event/1/query?assocaro=266266781">
        <time>
          <value>2025-01-05T04:31:45.770000Z</value>
          <uncertainty>0.3</uncertainty>
        </time>
        <waveformID networkCode="CI" stationCode="JEM" locationCode="" channelCode="HHE"></waveformID>
        <onset>emergent</onset>
        <phaseHint>S</phaseHint>
        <polarity>undecidable</polarity>
        <evaluationMode>automatic</evaluationMode>
        <evaluationStatus>preliminary</evaluationStatus>
        <creationInfo>
          <agencyID>CI</agencyID>
          <creationTime>2025-01-05T04:35:42.000000Z</creationTime>
        </creationInfo>
      </pick>
      <pick publicID="quakeml:service.scedc.caltech.edu/fdsnws/event/1/query?assocaro=266266789">
        <time>
          <value>2025-01-05T04:31:45.330000Z</value>
          <uncertainty>0.3</uncertainty>
        </time>
        <waveformID networkCode="CI" stationCode="LMH" locationCode="" channelCode="HHE"></waveformID>
        <onset>emergent</onset>
        <phaseHint>S</phaseHint>
        <polarity>undecidable</polarity>
        <evaluationMode>automatic</evaluationMode>
        <evaluationStatus>preliminary</evaluationStatus>
        <creationInfo>
          <agencyID>CI</agencyID>
          <creationTime>2025-01-05T04:35:42.000000Z</creationTime>
        </creationInfo>
      </pick>
      <amplitude publicID="quakeml:service.scedc.caltech.edu/fdsnws/event/1/query?ampid=929996917">
        <genericAmplitude>
          <value>1.5857e-05</value>
        </genericAmplitude>
        <type>AML</type>
        <category>point</category>
        <unit>m</unit>
        <methodID>smi:ci.anss.org/amp/WASF</methodID>
        <snr>15.0422788984032</snr>
        <waveformID networkCode="AZ" stationCode="CRY" locationCode="" channelCode="HHN"></waveformID>
        <scalingTime>
          <value>2025-01-05T04:31:32.750000Z</value>
        </scalingTime>
        <magnitudeHint>ML</magnitudeHint>
        <evaluationMode>automatic</evaluationMode>
        <evaluationStatus>preliminary</evaluationStatus>
      </amplitude>
      <amplitude publicID="quakeml:service.scedc.caltech.edu/fdsnws/event/1/query?ampid=929996909">
        <genericAmplitude>
          <value>3.3721e-05</value>
        </genericAmplitude>
        <type>AML</type>
        <category>point</category>
        <unit>m</unit>
        <methodID>smi:ci.anss.org/amp/WASF</methodID>
        <snr>41.4689888559146</snr>
        <waveformID networkCode="AZ" stationCode="KNW" locationCode="" channelCode="HHE"></waveformID>
        <scalingTime>
          <value>2025-01-05T04:31:32.190000Z</value>
        </scalingTime>
        <magnitudeHint>ML</magnitudeHint>
        <evaluationMode>automatic</evaluationMode>
        <evaluationStatus>preliminary</evaluationStatus>
      </amplitude>
      <amplitude publicID="quakeml:service.scedc.caltech.edu/fdsnws/event/1/query?ampid=929996901">
        <genericAmplitude>
          <value>4.1648e-05</value>
        </genericAmplitude>
        <type>AML</type>
        <category>point</category>
        <unit>m</unit>
        <methodID>smi:ci.anss.org/amp/WASF</methodID>
        <snr>44.5235366707853</snr>
        <waveformID networkCode="AZ" stationCode="KNW" locationCode="" channelCode="HHN"></waveformID>
        <scalingTime>
          <value>2025-01-05T04:31:32.120000Z</value>
        </scalingTime>
        <magnitudeHint>ML</magnitudeHint>
        <evaluationMode>automatic</evaluationMode>
        <evaluationStatus>preliminary</evaluationStatus>
      </amplitude>
      <amplitude publicID="quakeml:service.scedc.caltech.edu/fdsnws/event/1/query?ampid=929996981">
        <genericAmplitude>
          <value>1.4878e-05</value>
        </genericAmplitude>
        <type>AML</type>
        <category>point</category>
        <unit>m</unit>
        <methodID>smi:ci.anss.org/amp/WASF</methodID>
        <snr>9.42148299420154</snr>
        <waveformID networkCode="AZ" stationCode="RDM" locationCode="" channelCode="HHE"></waveformID>
        <scalingTime>
          <value>2025-01-05T04:31:33.640000Z</value>
        </scalingTime>
        <magnitudeHint>ML</magnitudeHint>
        <evaluationMode>automatic</evaluationMode>
        <evaluationStatus>preliminary</evaluationStatus>
      </amplitude>
      <amplitude publicID="quakeml:service.scedc.caltech.edu/fdsnws/event/1/query?ampid=929996973">
        <genericAmplitude>
          <value>1.2564e-05</value>
        </genericAmplitude>
        <type>AML</type>
        <category>point</category>
        <unit>m</unit>
        <methodID>smi:ci.anss.org/amp/WASF</methodID>
        <snr>10.8895846137489</snr>
        <waveformID networkCode="AZ" stationCode="RDM" locationCode="" channelCode="HHN"></waveformID>
        <scalingTime>
          <value>2025-01-05T04:31:33.760000Z</value>
        </scalingTime>
        <magnitudeHint>ML</magnitudeHint>
        <evaluationMode>automatic</evaluationMode>
        <evaluationStatus>preliminary</evaluationStatus>
      </amplitude>
      <amplitude publicID="quakeml:service.scedc.caltech.edu/fdsnws/event/1/query?ampid=929996989">
        <genericAmplitude>
          <value>2.3896e-05</value>
        </genericAmplitude>
        <type>AML</type>
        <category>point</category>
        <unit>m</unit>
        <methodID>smi:ci.anss.org/amp/WASF</methodID>
        <snr>5.34794543818337</snr>
        <waveformID networkCode="AZ" stationCode="SND" locationCode="" channelCode="HHN"></waveformID>
        <scalingTime>
          <value>2025-01-05T04:31:34.280000Z</value>
        </scalingTime>
        <magnitudeHint>ML</magnitudeHint>
        <evaluationMode>automatic</evaluationMode>
        <evaluationStatus>preliminary</evaluationStatus>
      </amplitude>
      <amplitude publicID="quakeml:service.scedc.caltech.edu/fdsnws/event/1/query?ampid=929997037">
        <genericAmplitude>
          <value>0.00028668</value>
        </genericAmplitude>
        <type>AML</type>
        <category>point</category>
        <unit>m</unit>
        <methodID>smi:ci.anss.org/amp/WAS</methodID>
        <snr>6.21928860678803</snr>
        <waveformID networkCode="CI" stationCode="BBS" locationCode="" channelCode="HHN"></waveformID>
        <scalingTime>
          <value>2025-01-05T04:31:36.070000Z</value>
        </scalingTime>
        <magnitudeHint>ML</magnitudeHint>
        <evaluationMode>automatic</evaluationMode>
        <evaluationStatus>preliminary</evaluationStatus>
      </amplitude>
      <amplitude publicID="quakeml:service.scedc.caltech.edu/fdsnws/event/1/query?ampid=929996933">
        <genericAmplitude>
          <value>3.7753e-05</value>
        </genericAmplitude>
        <type>AML</type>
        <category>point</category>
        <unit>m</unit>
        <methodID>smi:ci.anss.org/amp/WASF</methodID>
        <snr>26.2612152448374</snr>
        <waveformID networkCode="CI" stationCode="CSH" locationCode="" channelCode="HHE"></waveformID>
        <scalingTime>
          <value>2025-01-05T04:31:32.720000Z</value>
        </scalingTime>
        <magnitudeHint>ML</magnitudeHint>
        <evaluationMode>automatic</evaluationMode>
        <evaluationStatus>preliminary</evaluationStatus>
      </amplitude>
      <amplitude publicID="quakeml:service.scedc.caltech.edu/fdsnws/event/1/query?ampid=929996925">
        <genericAmplitude>
          <value>3.343e-05</value>
        </genericAmplitude>
        <type>AML</type>
        <category>point</category>
        <unit>m</unit>
        <methodID>smi:ci.anss.org/amp/WASF</methodID>
        <snr>17.9503655511772</snr>
        <waveformID networkCode="CI" stationCode="CSH" locationCode="" channelCode="HHN"></waveformID>
        <scalingTime>
          <value>2025-01-05T04:31:32.730000Z</value>
        </scalingTime>
        <magnitudeHint>ML</magnitudeHint>
        <evaluationMode>automatic</evaluationMode>
        <evaluationStatus>preliminary</evaluationStatus>
      </amplitude>
      <amplitude publicID="quakeml:service.scedc.caltech.edu/fdsnws/event/1/query?ampid=929996965">
        <genericAmplitude>
          <value>4.5827e-05</value>
        </genericAmplitude>
        <type>AML</type>
        <category>point</category>
        <unit>m</unit>
        <methodID>smi:ci.anss.org/amp/WASF</methodID>
        <snr>6.83481999149224</snr>
        <waveformID networkCode="CI" stationCode="DNR" locationCode="" channelCode="HHE"></waveformID>
        <scalingTime>
          <value>2025-01-05T04:31:34.220000Z</value>
        </scalingTime>
        <magnitudeHint>ML</magnitudeHint>
        <evaluationMode>automatic</evaluationMode>
        <evaluationStatus>preliminary</evaluationStatus>
      </amplitude>
      <amplitude publicID="quakeml:service.scedc.caltech.edu/fdsnws/event/1/query?ampid=929996957">
        <genericAmplitude>
          <value>3.6731e-05</value>
        </genericAmplitude>
        <type>AML</type>
        <category>point</category>
        <unit>m</unit>
        <methodID>smi:ci.anss.org/amp/WASF</methodID>
        <snr>7.16683967717829</snr>
        <waveformID networkCode="CI" stationCode="DNR" locationCode="" channelCode="HHN"></waveformID>
        <scalingTime>
          <value>2025-01-05T04:31:33.580000Z</value>
        </scalingTime>
        <magnitudeHint>ML</magnitudeHint>
        <evaluationMode>automatic</evaluationMode>
        <evaluationStatus>preliminary</evaluationStatus>
      </amplitude>
      <amplitude publicID="quakeml:service.scedc.caltech.edu/fdsnws/event/1/query?ampid=929997013">
        <genericAmplitude>
          <value>5.6635e-05</value>
        </genericAmplitude>
        <type>AML</type>
        <category>point</category>
        <unit>m</unit>
        <methodID>smi:ci.anss.org/amp/WASF</methodID>
        <snr>17.3723201725924</snr>
        <waveformID networkCode="CI" stationCode="HMT2" locationCode="" channelCode="HHE"></waveformID>
        <scalingTime>
          <value>2025-01-05T04:31:36.960000Z</value>
        </scalingTime>
        <magnitudeHint>ML</magnitudeHint>
        <evaluationMode>automatic</evaluationMode>
        <evaluationStatus>preliminary</evaluationStatus>
      </amplitude>
      <amplitude publicID="quakeml:service.scedc.caltech.edu/fdsnws/event/1/query?ampid=929997005">
        <genericAmplitude>
          <value>2.1124e-05</value>
        </genericAmplitude>
        <type>AML</type>
        <category>point</category>
        <unit>m</unit>
        <methodID>smi:ci.anss.org/amp/WASF</methodID>
        <snr>9.65108151838135</snr>
        <waveformID networkCode="CI" stationCode="HMT2" locationCode="" channelCode="HHN"></waveformID>
        <scalingTime>
          <value>2025-01-05T04:31:37.020000Z</value>
        </scalingTime>
        <magnitudeHint>ML</magnitudeHint>
        <evaluationMode>automatic</evaluationMode>
        <evaluationStatus>preliminary</evaluationStatus>
      </amplitude>
      <amplitude publicID="quakeml:service.scedc.caltech.edu/fdsnws/event/1/query?ampid=929996949">
        <genericAmplitude>
          <value>0.00019521</value>
        </genericAmplitude>
        <type>AML</type>
        <category>point</category>
        <unit>m</unit>
        <methodID>smi:ci.anss.org/amp/WASF</methodID>
        <snr>6.70975705536437</snr>
        <waveformID networkCode="CI" stationCode="IDY" locationCode="" channelCode="HHE"></waveformID>
        <scalingTime>
          <value>2025-01-05T04:31:32.730000Z</value>
        </scalingTime>
        <magnitudeHint>ML</magnitudeHint>
        <evaluationMode>automatic</evaluationMode>
        <evaluationStatus>preliminary</evaluationStatus>
      </amplitude>
      <amplitude publicID="quakeml:service.scedc.caltech.edu/fdsnws/event/1/query?ampid=929996941">
        <genericAmplitude>
          <value>0.000383</value>
        </genericAmplitude>
        <type>AML</type>
        <category>point</category>
        <unit>m</unit>
        <methodID>smi:ci.anss.org/amp/WAS</methodID>
        <snr>10.9325040889555</snr>
        <waveformID networkCode="CI" stationCode="IDY" locationCode="" channelCode="HHN"></waveformID>
        <scalingTime>
          <value>2025-01-05T04:31:30.920000Z</value>
        </scalingTime>
        <magnitudeHint>ML</magnitudeHint>
        <evaluationMode>automatic</evaluationMode>
        <evaluationStatus>preliminary</evaluationStatus>
      </amplitude>
      <amplitude publicID="quakeml:service.scedc.caltech.edu/fdsnws/event/1/query?ampid=929997021">
        <genericAmplitude>
          <value>0.00025175</value>
        </genericAmplitude>
        <type>AML</type>
        <category>point</category>
        <unit>m</unit>
        <methodID>smi:ci.anss.org/amp/WAS</methodID>
        <snr>4.0177679073787</snr>
        <waveformID networkCode="CI" stationCode="MSJ" locationCode="" channelCode="HHN"></waveformID>
        <scalingTime>
          <value>2025-01-05T04:31:38.230000Z</value>
        </scalingTime>
        <magnitudeHint>ML</magnitudeHint>
        <evaluationMode>automatic</evaluationMode>
        <evaluationStatus>preliminary</evaluationStatus>
      </amplitude>
      <amplitude publicID="quakeml:service.scedc.caltech.edu/fdsnws/event/1/query?ampid=929997029">
        <genericAmplitude>
          <value>1.1399e-05</value>
        </genericAmplitude>
        <type>AML</type>
        <category>point</category>
        <unit>m</unit>
        <methodID>smi:ci.anss.org/amp/WASF</methodID>
        <snr>5.80803815374523</snr>
        <waveformID networkCode="CI" stationCode="PLM" locationCode="" channelCode="HHE"></waveformID>
        <scalingTime>
          <value>2025-01-05T04:31:38.500000Z</value>
        </scalingTime>
        <magnitudeHint>ML</magnitudeHint>
        <evaluationMode>automatic</evaluationMode>
        <evaluationStatus>preliminary</evaluationStatus>
      </amplitude>
      <amplitude publicID="quakeml:service.scedc.caltech.edu/fdsnws/event/1/query?ampid=929996997">
        <genericAmplitude>
          <value>1.7169e-05</value>
        </genericAmplitude>
        <type>AML</type>
        <category>point</category>
        <unit>m</unit>
        <methodID>smi:ci.anss.org/amp/WASF</methodID>
        <snr>4.38560293968306</snr>
        <waveformID networkCode="CI" stationCode="SLR" locationCode="" channelCode="HHN"></waveformID>
        <scalingTime>
          <value>2025-01-05T04:31:35.370000Z</value>
        </scalingTime>
        <magnitudeHint>ML</magnitudeHint>
        <evaluationMode>automatic</evaluationMode>
        <evaluationStatus>preliminary</evaluationStatus>
      </amplitude>
      <amplitude publicID="quakeml:service.scedc.caltech.edu/fdsnws/event/1/query?ampid=929997053">
        <genericAmplitude>
          <value>3.6255e-05</value>
        </genericAmplitude>
        <type>AML</type>
        <category>point</category>
        <unit>m</unit>
        <methodID>smi:ci.anss.org/amp/WASF</methodID>
        <snr>4.0157003520465</snr>
        <waveformID networkCode="CI" stationCode="VLY" locationCode="" channelCode="HHE"></waveformID>
        <scalingTime>
          <value>2025-01-05T04:31:44.350000Z</value>
        </scalingTime>
        <magnitudeHint>ML</magnitudeHint>
        <evaluationMode>automatic</evaluationMode>
        <evaluationStatus>preliminary</evaluationStatus>
      </amplitude>
      <amplitude publicID="quakeml:service.scedc.caltech.edu/fdsnws/event/1/query?ampid=929997045">
        <genericAmplitude>
          <value>4.1137e-05</value>
        </genericAmplitude>
        <type>AML</type>
        <category>point</category>
        <unit>m</unit>
        <methodID>smi:ci.anss.org/amp/WASF</methodID>
        <snr>4.33581161196865</snr>
        <waveformID networkCode="CI" stationCode="VLY" locationCode="" channelCode="HHN"></waveformID>
        <scalingTime>
          <value>2025-01-05T04:31:50.450000Z</value>
        </scalingTime>
        <magnitudeHint>ML</magnitudeHint>
        <evaluationMode>automatic</evaluationMode>
        <evaluationStatus>preliminary</evaluationStatus>
      </amplitude>
    </event>
  </eventParameters>
</q:quakeml>
