<?xml version='1.0' encoding='utf-8'?>
<q:quakeml xmlns="http://quakeml.org/xmlns/bed/1.2" xmlns:q="http://quakeml.org/xmlns/quakeml/1.2" xmlns:ns0="http://anss.org/xmlns/catalog/0.1">
  <eventParameters publicID="smi:local/d2257fd0-2ca1-4f11-9610-4ba4203df40b">
    <event publicID="quakeml:service.scedc.caltech.edu/fdsnws/event/1/query?eventid=40842983" ns0:datasource="ci" ns0:dataid="ci40842983" ns0:eventsource="ci" ns0:eventid="40842983">
      <preferredOriginID>quakeml:service.scedc.caltech.edu/fdsnws/event/1/query?originid=105812069</preferredOriginID>
      <preferredMagnitudeID>quakeml:service.scedc.caltech.edu/fdsnws/event/1/query?magnitudeid=109268453</preferredMagnitudeID>
      <type>earthquake</type>
      <creationInfo>
        <agencyID>CI</agencyID>
        <agencyURI>quakeml:doi.org/10.7909/C3WD3xH1</agencyURI>
        <creationTime>2025-01-19T02:17:20.000000Z</creationTime>
        <version>5</version>
      </creationInfo>
      <origin publicID="quakeml:service.scedc.caltech.edu/fdsnws/event/1/query?originid=105812069" ns0:datasource="ci" ns0:dataid="ci40842983" ns0:eventsource="ci" ns0:eventid="40842983">
        <time>
          <value>2025-01-19T02:13:33.570000Z</value>
        </time>
        <latitude>
          <value>33.4626667</value>
        </latitude>
        <longitude>
          <value>-116.6113333</value>
        </longitude>
        <depth>
          <value>9320.0</value>
          <uncertainty>440.0</uncertainty>
        </depth>
        <depthType>from location</depthType>
        <timeFixed>false</timeFixed>
        <epicenterFixed>false</epicenterFixed>
        <methodID>smi:ci.anss.org/origin/HYP2000</methodID>
        <quality>
          <associatedPhaseCount>35</associatedPhaseCount>
          <usedPhaseCount>35</usedPhaseCount>
          <associatedStationCount>20</associatedStationCount>
          <usedStationCount>20</usedStationCount>
          <standardError>0.13</standardError>
          <azimuthalGap>56.0</azimuthalGap>
          <secondaryAzimuthalGap>425.0</secondaryAzimuthalGap>
          <minimumDistance>0.03285</minimumDistance>
          <maximumDistance>0.8605</maximumDistance>
          <medianDistance>0.2558</medianDistance>
        </quality>
        <type>hypocenter</type>
        <evaluationMode>manual</evaluationMode>
        <evaluationStatus>final</evaluationStatus>
        <creationInfo>
          <agencyID>CI</agencyID>
          <creationTime>2025-01-19T02:17:12.000000Z</creationTime>
        </creationInfo>
        <originUncertainty>
          <preferredDescription>confidence ellipsoid</preferredDescription>
          <horizontalUncertainty>190.0</horizontalUncertainty>
          <confidenceLevel>95.0</confidenceLevel>
          <confidenceEllipsoid>
            <semiMajorAxisLength>1056.0</semiMajorAxisLength>
            <semiMinorAxisLength>408.0</semiMinorAxisLength>
            <semiIntermediateAxisLength>456.0</semiIntermediateAxisLength>
            <majorAxisPlunge>86.0</majorAxisPlunge>
            <majorAxisAzimuth>64.0</majorAxisAzimuth>
            <majorAxisRotation>8.0</majorAxisRotation>
          </confidenceEllipsoid>
        </originUncertainty>
        <arrival publicID="quakeml:service.scedc.caltech.edu/fdsnws/event/1/query?assocaro=144699375">
          <pickID>quakeml:service.scedc.caltech.edu/fdsnws/event/1/query?assocaro=144699375</pickID>
          <phase>S</phase>
          <timeCorrection>0.26</timeCorrection>
          <azimuth>318.0</azimuth>
          <distance>0.8605</distance>
          <takeoffAngle>
            <value>77.0</value>
          </takeoffAngle>
          <timeResidual>0.49</timeResidual>
          <timeWeight>0.06</timeWeight>
          <creationInfo>
            <agencyID>CI</agencyID>
            <creationTime>2025-01-19T02:17:12.000000Z</creationTime>
          </creationInfo>
        </arrival>
        <arrival publicID="quakeml:service.scedc.caltech.edu/fdsnws/event/1/query?assocaro=266486549">
          <pickID>quakeml:service.scedc.caltech.edu/fdsnws/event/1/query?assocaro=266486549</pickID>
          <phase>P</phase>
          <timeCorrection>-0.08</timeCorrection>
          <azimuth>13.0</azimuth>
          <distance>0.03285</distance>
          <takeoffAngle>
            <value>159.0</value>
          </takeoffAngle>
          <timeResidual>0.02</timeResidual>
          <timeWeight>0.2</timeWeight>
          <creationInfo>
            <agencyID>CI</agencyID>
            <creationTime>2025-01-19T02:17:12.000000Z</creationTime>
          </creationInfo>
        </arrival>
        <arrival publicID="quakeml:service.scedc.caltech.edu/fdsnws/event/1/query?assocaro=266486557">
          <pickID>quakeml:service.scedc.caltech.edu/fdsnws/event/1/query?assocaro=266486557</pickID>
          <phase>S</phase>
          <timeCorrection>-0.33</timeCorrection>
          <azimuth>13.0</azimuth>
          <distance>0.03285</distance>
          <takeoffAngle>
            <value>159.0</value>
          </takeoffAngle>
          <timeResidual>0.18</timeResidual>
          <timeWeight>0.08</timeWeight>
          <creationInfo>
            <agencyID>CI</agencyID>
            <creationTime>2025-01-19T02:17:12.000000Z</creationTime>
          </creationInfo>
        </arrival>
        <arrival publicID="quakeml:service.scedc.caltech.edu/fdsnws/event/1/query?assocaro=266486565">
          <pickID>quakeml:service.scedc.caltech.edu/fdsnws/event/1/query?assocaro=266486565</pickID>
          <phase>P</phase>
          <timeCorrection>-0.07</timeCorrection>
          <azimuth>0.0</azimuth>
          <distance>0.08901</distance>
          <takeoffAngle>
            <value>132.0</value>
          </takeoffAngle>
          <timeResidual>0.11</timeResidual>
          <timeWeight>0.1</timeWeight>
          <creationInfo>
            <agencyID>CI</agencyID>
            <creationTime>2025-01-19T02:17:12.000000Z</creationTime>
          </creationInfo>
        </arrival>
        <arrival publicID="quakeml:service.scedc.caltech.edu/fdsnws/event/1/query?assocaro=266486573">
          <pickID>quakeml:service.scedc.caltech.edu/fdsnws/event/1/query?assocaro=266486573</pickID>
          <phase>P</phase>
          <timeCorrection>-0.02</timeCorrection>
          <azimuth>352.0</azimuth>
          <distance>0.105</distance>
          <takeoffAngle>
            <value>127.0</value>
          </takeoffAngle>
          <timeResidual>0.04</timeResidual>
          <timeWeight>0.1</timeWeight>
          <creationInfo>
            <agencyID>CI</agencyID>
            <creationTime>2025-01-19T02:17:12.000000Z</creationTime>
          </creationInfo>
        </arrival>
        <arrival publicID="quakeml:service.scedc.caltech.edu/fdsnws/event/1/query?assocaro=266486581">
          <pickID>quakeml:service.scedc.caltech.edu/fdsnws/event/1/query?assocaro=266486581</pickID>
          <phase>S</phase>
          <timeCorrection>-0.07</timeCorrection>
          <azimuth>352.0</azimuth>
          <distance>0.105</distance>
          <takeoffAngle>
            <value>127.0</value>
          </takeoffAngle>
          <timeResidual>0.48</timeResidual>
          <timeWeight>0.05</timeWeight>
          <creationInfo>
            <agencyID>CI</agencyID>
            <creationTime>2025-01-19T02:17:12.000000Z</creationTime>
          </creationInfo>
        </arrival>
        <arrival publicID="quakeml:service.scedc.caltech.edu/fdsnws/event/1/query?assocaro=266486589">
          <pickID>quakeml:service.scedc.caltech.edu/fdsnws/event/1/query?assocaro=266486589</pickID>
          <phase>P</phase>
          <timeCorrection>-0.03</timeCorrection>
          <azimuth>159.0</azimuth>
          <distance>0.1184</distance>
          <takeoffAngle>
            <value>123.0</value>
          </takeoffAngle>
          <timeResidual>0.04</timeResidual>
          <timeWeight>0.2</timeWeight>
          <creationInfo>
            <agencyID>CI</agencyID>
            <creationTime>2025-01-19T02:17:12.000000Z</creationTime>
          </creationInfo>
        </arrival>
        <arrival publicID="quakeml:service.scedc.caltech.edu/fdsnws/event/1/query?assocaro=266486597">
          <pickID>quakeml:service.scedc.caltech.edu/fdsnws/event/1/query?assocaro=266486597</pickID>
          <phase>S</phase>
          <timeCorrection>-0.2</timeCorrection>
          <azimuth>159.0</azimuth>
          <distance>0.1184</distance>
          <takeoffAngle>
            <value>123.0</value>
          </takeoffAngle>
          <timeResidual>0.24</timeResidual>
          <timeWeight>0.05</timeWeight>
          <creationInfo>
            <agencyID>CI</agencyID>
            <creationTime>2025-01-19T02:17:12.000000Z</creationTime>
          </creationInfo>
        </arrival>
        <arrival publicID="quakeml:service.scedc.caltech.edu/fdsnws/event/1/query?assocaro=266486605">
          <pickID>quakeml:service.scedc.caltech.edu/fdsnws/event/1/query?assocaro=266486605</pickID>
          <phase>S</phase>
          <timeCorrection>-0.33</timeCorrection>
          <azimuth>315.0</azimuth>
          <distance>0.1469</distance>
          <takeoffAngle>
            <value>116.0</value>
          </takeoffAngle>
          <timeResidual>0.23</timeResidual>
          <timeWeight>0.05</timeWeight>
          <creationInfo>
            <agencyID>CI</agencyID>
            <creationTime>2025-01-19T02:17:12.000000Z</creationTime>
          </creationInfo>
        </arrival>
        <arrival publicID="quakeml:service.scedc.caltech.edu/fdsnws/event/1/query?assocaro=266486613">
          <pickID>quakeml:service.scedc.caltech.edu/fdsnws/event/1/query?assocaro=266486613</pickID>
          <phase>P</phase>
          <timeCorrection>0.0</timeCorrection>
          <azimuth>284.0</azimuth>
          <distance>0.1696</distance>
          <takeoffAngle>
            <value>112.0</value>
          </takeoffAngle>
          <timeResidual>-0.11</timeResidual>
          <timeWeight>0.2</timeWeight>
          <creationInfo>
            <agencyID>CI</agencyID>
            <creationTime>2025-01-19T02:17:12.000000Z</creationTime>
          </creationInfo>
        </arrival>
        <arrival publicID="quakeml:service.scedc.caltech.edu/fdsnws/event/1/query?assocaro=266486621">
          <pickID>quakeml:service.scedc.caltech.edu/fdsnws/event/1/query?assocaro=266486621</pickID>
          <phase>S</phase>
          <timeCorrection>0.0</timeCorrection>
          <azimuth>284.0</azimuth>
          <distance>0.1696</distance>
          <takeoffAngle>
            <value>112.0</value>
          </takeoffAngle>
          <timeResidual>-0.19</timeResidual>
          <timeWeight>0.05</timeWeight>
          <creationInfo>
            <agencyID>CI</agencyID>
            <creationTime>2025-01-19T02:17:12.000000Z</creationTime>
          </creationInfo>
        </arrival>
        <arrival publicID="quakeml:service.scedc.caltech.edu/fdsnws/event/1/query?assocaro=266486629">
          <pickID>quakeml:service.scedc.caltech.edu/fdsnws/event/1/query?assocaro=266486629</pickID>
          <phase>P</phase>
          <timeCorrection>0.0</timeCorrection>
          <azimuth>4.0</azimuth>
          <distance>0.1815</distance>
          <takeoffAngle>
            <value>110.0</value>
          </takeoffAngle>
          <timeResidual>-0.11</timeResidual>
          <timeWeight>0.2</timeWeight>
          <creationInfo>
            <agencyID>CI</agencyID>
            <creationTime>2025-01-19T02:17:12.000000Z</creationTime>
          </creationInfo>
        </arrival>
        <arrival publicID="quakeml:service.scedc.caltech.edu/fdsnws/event/1/query?assocaro=266486637">
          <pickID>quakeml:service.scedc.caltech.edu/fdsnws/event/1/query?assocaro=266486637</pickID>
          <phase>S</phase>
          <timeCorrection>0.0</timeCorrection>
          <azimuth>4.0</azimuth>
          <distance>0.1815</distance>
          <takeoffAngle>
            <value>110.0</value>
          </takeoffAngle>
          <timeResidual>-0.14</timeResidual>
          <timeWeight>0.05</timeWeight>
          <creationInfo>
            <agencyID>CI</agencyID>
            <creationTime>2025-01-19T02:17:12.000000Z</creationTime>
          </creationInfo>
        </arrival>
        <arrival publicID="quakeml:service.scedc.caltech.edu/fdsnws/event/1/query?assocaro=266486645">
          <pickID>quakeml:service.scedc.caltech.edu/fdsnws/event/1/query?assocaro=266486645</pickID>
          <phase>P</phase>
          <timeCorrection>-0.17</timeCorrection>
          <azimuth>40.0</azimuth>
          <distance>0.1954</distance>
          <takeoffAngle>
            <value>108.0</value>
          </takeoffAngle>
          <timeResidual>0.1</timeResidual>
          <timeWeight>0.2</timeWeight>
          <creationInfo>
            <agencyID>CI</agencyID>
            <creationTime>2025-01-19T02:17:12.000000Z</creationTime>
          </creationInfo>
        </arrival>
        <arrival publicID="quakeml:service.scedc.caltech.edu/fdsnws/event/1/query?assocaro=266486653">
          <pickID>quakeml:service.scedc.caltech.edu/fdsnws/event/1/query?assocaro=266486653</pickID>
          <phase>S</phase>
          <timeCorrection>-0.43</timeCorrection>
          <azimuth>40.0</azimuth>
          <distance>0.1954</distance>
          <takeoffAngle>
            <value>108.0</value>
          </takeoffAngle>
          <timeResidual>0.24</timeResidual>
          <timeWeight>0.08</timeWeight>
          <creationInfo>
            <agencyID>CI</agencyID>
            <creationTime>2025-01-19T02:17:12.000000Z</creationTime>
          </creationInfo>
        </arrival>
        <arrival publicID="quakeml:service.scedc.caltech.edu/fdsnws/event/1/query?assocaro=266486661">
          <pickID>quakeml:service.scedc.caltech.edu/fdsnws/event/1/query?assocaro=266486661</pickID>
          <phase>P</phase>
          <timeCorrection>-0.11</timeCorrection>
          <azimuth>243.0</azimuth>
          <distance>0.2367</distance>
          <takeoffAngle>
            <value>104.0</value>
          </takeoffAngle>
          <timeResidual>0.06</timeResidual>
          <timeWeight>0.1</timeWeight>
          <creationInfo>
            <agencyID>CI</agencyID>
            <creationTime>2025-01-19T02:17:12.000000Z</creationTime>
          </creationInfo>
        </arrival>
        <arrival publicID="quakeml:service.scedc.caltech.edu/fdsnws/event/1/query?assocaro=266486669">
          <pickID>quakeml:service.scedc.caltech.edu/fdsnws/event/1/query?assocaro=266486669</pickID>
          <phase>S</phase>
          <timeCorrection>-0.28</timeCorrection>
          <azimuth>243.0</azimuth>
          <distance>0.2367</distance>
          <takeoffAngle>
            <value>104.0</value>
          </takeoffAngle>
          <timeResidual>0.39</timeResidual>
          <timeWeight>0.05</timeWeight>
          <creationInfo>
            <agencyID>CI</agencyID>
            <creationTime>2025-01-19T02:17:12.000000Z</creationTime>
          </creationInfo>
        </arrival>
        <arrival publicID="quakeml:service.scedc.caltech.edu/fdsnws/event/1/query?assocaro=266486677">
          <pickID>quakeml:service.scedc.caltech.edu/fdsnws/event/1/query?assocaro=266486677</pickID>
          <phase>S</phase>
          <timeCorrection>-0.3</timeCorrection>
          <azimuth>139.0</azimuth>
          <distance>0.253</distance>
          <takeoffAngle>
            <value>102.0</value>
          </takeoffAngle>
          <timeResidual>-0.1</timeResidual>
          <timeWeight>0.05</timeWeight>
          <creationInfo>
            <agencyID>CI</agencyID>
            <creationTime>2025-01-19T02:17:12.000000Z</creationTime>
          </creationInfo>
        </arrival>
        <arrival publicID="quakeml:service.scedc.caltech.edu/fdsnws/event/1/query?assocaro=266486685">
          <pickID>quakeml:service.scedc.caltech.edu/fdsnws/event/1/query?assocaro=266486685</pickID>
          <phase>P</phase>
          <timeCorrection>-0.12</timeCorrection>
          <azimuth>311.0</azimuth>
          <distance>0.2586</distance>
          <takeoffAngle>
            <value>102.0</value>
          </takeoffAngle>
          <timeResidual>-0.04</timeResidual>
          <timeWeight>0.1</timeWeight>
          <creationInfo>
            <agencyID>CI</agencyID>
            <creationTime>2025-01-19T02:17:12.000000Z</creationTime>
          </creationInfo>
        </arrival>
        <arrival publicID="quakeml:service.scedc.caltech.edu/fdsnws/event/1/query?assocaro=266486693">
          <pickID>quakeml:service.scedc.caltech.edu/fdsnws/event/1/query?assocaro=266486693</pickID>
          <phase>S</phase>
          <timeCorrection>-0.18</timeCorrection>
          <azimuth>311.0</azimuth>
          <distance>0.2586</distance>
          <takeoffAngle>
            <value>102.0</value>
          </takeoffAngle>
          <timeResidual>-0.17</timeResidual>
          <timeWeight>0.05</timeWeight>
          <creationInfo>
            <agencyID>CI</agencyID>
            <creationTime>2025-01-19T02:17:12.000000Z</creationTime>
          </creationInfo>
        </arrival>
        <arrival publicID="quakeml:service.scedc.caltech.edu/fdsnws/event/1/query?assocaro=266486701">
          <pickID>quakeml:service.scedc.caltech.edu/fdsnws/event/1/query?assocaro=266486701</pickID>
          <phase>P</phase>
          <timeCorrection>-0.17</timeCorrection>
          <azimuth>342.0</azimuth>
          <distance>0.2645</distance>
          <takeoffAngle>
            <value>102.0</value>
          </takeoffAngle>
          <timeResidual>0.0</timeResidual>
          <timeWeight>0.2</timeWeight>
          <creationInfo>
            <agencyID>CI</agencyID>
            <creationTime>2025-01-19T02:17:12.000000Z</creationTime>
          </creationInfo>
        </arrival>
        <arrival publicID="quakeml:service.scedc.caltech.edu/fdsnws/event/1/query?assocaro=266486709">
          <pickID>quakeml:service.scedc.caltech.edu/fdsnws/event/1/query?assocaro=266486709</pickID>
          <phase>S</phase>
          <timeCorrection>-0.47</timeCorrection>
          <azimuth>342.0</azimuth>
          <distance>0.2645</distance>
          <takeoffAngle>
            <value>101.0</value>
          </takeoffAngle>
          <timeResidual>0.13</timeResidual>
          <timeWeight>0.08</timeWeight>
          <creationInfo>
            <agencyID>CI</agencyID>
            <creationTime>2025-01-19T02:17:12.000000Z</creationTime>
          </creationInfo>
        </arrival>
        <arrival publicID="quakeml:service.scedc.caltech.edu/fdsnws/event/1/query?assocaro=266486717">
          <pickID>quakeml:service.scedc.caltech.edu/fdsnws/event/1/query?assocaro=266486717</pickID>
          <phase>P</phase>
          <timeCorrection>-0.05</timeCorrection>
          <azimuth>187.0</azimuth>
          <distance>0.2645</distance>
          <takeoffAngle>
            <value>102.0</value>
          </takeoffAngle>
          <timeResidual>0.05</timeResidual>
          <timeWeight>0.15</timeWeight>
          <creationInfo>
            <agencyID>CI</agencyID>
            <creationTime>2025-01-19T02:17:12.000000Z</creationTime>
          </creationInfo>
        </arrival>
        <arrival publicID="quakeml:service.scedc.caltech.edu/fdsnws/event/1/query?assocaro=266486725">
          <pickID>quakeml:service.scedc.caltech.edu/fdsnws/event/1/query?assocaro=266486725</pickID>
          <phase>S</phase>
          <timeCorrection>-0.25</timeCorrection>
          <azimuth>187.0</azimuth>
          <distance>0.2645</distance>
          <takeoffAngle>
            <value>101.0</value>
          </takeoffAngle>
          <timeResidual>0.22</timeResidual>
          <timeWeight>0.05</timeWeight>
          <creationInfo>
            <agencyID>CI</agencyID>
            <creationTime>2025-01-19T02:17:12.000000Z</creationTime>
          </creationInfo>
        </arrival>
        <arrival publicID="quakeml:service.scedc.caltech.edu/fdsnws/event/1/query?assocaro=266486733">
          <pickID>quakeml:service.scedc.caltech.edu/fdsnws/event/1/query?assocaro=266486733</pickID>
          <phase>P</phase>
          <timeCorrection>-0.18</timeCorrection>
          <azimuth>46.0</azimuth>
          <distance>0.2687</distance>
          <takeoffAngle>
            <value>101.0</value>
          </takeoffAngle>
          <timeResidual>0.08</timeResidual>
          <timeWeight>0.1</timeWeight>
          <creationInfo>
            <agencyID>CI</agencyID>
            <creationTime>2025-01-19T02:17:12.000000Z</creationTime>
          </creationInfo>
        </arrival>
        <arrival publicID="quakeml:service.scedc.caltech.edu/fdsnws/event/1/query?assocaro=266486741">
          <pickID>quakeml:service.scedc.caltech.edu/fdsnws/event/1/query?assocaro=266486741</pickID>
          <phase>S</phase>
          <timeCorrection>-0.46</timeCorrection>
          <azimuth>46.0</azimuth>
          <distance>0.2687</distance>
          <takeoffAngle>
            <value>101.0</value>
          </takeoffAngle>
          <timeResidual>0.03</timeResidual>
          <timeWeight>0.05</timeWeight>
          <creationInfo>
            <agencyID>CI</agencyID>
            <creationTime>2025-01-19T02:17:12.000000Z</creationTime>
          </creationInfo>
        </arrival>
        <arrival publicID="quakeml:service.scedc.caltech.edu/fdsnws/event/1/query?assocaro=266486749">
          <pickID>quakeml:service.scedc.caltech.edu/fdsnws/event/1/query?assocaro=266486749</pickID>
          <phase>P</phase>
          <timeCorrection>0.0</timeCorrection>
          <azimuth>111.0</azimuth>
          <distance>0.2715</distance>
          <takeoffAngle>
            <value>101.0</value>
          </takeoffAngle>
          <timeResidual>-0.06</timeResidual>
          <timeWeight>0.15</timeWeight>
          <creationInfo>
            <agencyID>CI</agencyID>
            <creationTime>2025-01-19T02:17:12.000000Z</creationTime>
          </creationInfo>
        </arrival>
        <arrival publicID="quakeml:service.scedc.caltech.edu/fdsnws/event/1/query?assocaro=266486757">
          <pickID>quakeml:service.scedc.caltech.edu/fdsnws/event/1/query?assocaro=266486757</pickID>
          <phase>S</phase>
          <timeCorrection>0.0</timeCorrection>
          <azimuth>111.0</azimuth>
          <distance>0.2715</distance>
          <takeoffAngle>
            <value>101.0</value>
          </takeoffAngle>
          <timeResidual>-0.16</timeResidual>
          <timeWeight>0.05</timeWeight>
          <creationInfo>
            <agencyID>CI</agencyID>
            <creationTime>2025-01-19T02:17:12.000000Z</creationTime>
          </creationInfo>
        </arrival>
        <arrival publicID="quakeml:service.scedc.caltech.edu/fdsnws/event/1/query?assocaro=266486765">
          <pickID>quakeml:service.scedc.caltech.edu/fdsnws/event/1/query?assocaro=266486765</pickID>
          <phase>P</phase>
          <timeCorrection>-0.1</timeCorrection>
          <azimuth>70.0</azimuth>
          <distance>0.3411</distance>
          <takeoffAngle>
            <value>97.0</value>
          </takeoffAngle>
          <timeResidual>0.01</timeResidual>
          <timeWeight>0.15</timeWeight>
          <creationInfo>
            <agencyID>CI</agencyID>
            <creationTime>2025-01-19T02:17:12.000000Z</creationTime>
          </creationInfo>
        </arrival>
        <arrival publicID="quakeml:service.scedc.caltech.edu/fdsnws/event/1/query?assocaro=266486773">
          <pickID>quakeml:service.scedc.caltech.edu/fdsnws/event/1/query?assocaro=266486773</pickID>
          <phase>S</phase>
          <timeCorrection>-0.29</timeCorrection>
          <azimuth>70.0</azimuth>
          <distance>0.3411</distance>
          <takeoffAngle>
            <value>97.0</value>
          </takeoffAngle>
          <timeResidual>0.12</timeResidual>
          <timeWeight>0.05</timeWeight>
          <creationInfo>
            <agencyID>CI</agencyID>
            <creationTime>2025-01-19T02:17:12.000000Z</creationTime>
          </creationInfo>
        </arrival>
        <arrival publicID="quakeml:service.scedc.caltech.edu/fdsnws/event/1/query?assocaro=266486781">
          <pickID>quakeml:service.scedc.caltech.edu/fdsnws/event/1/query?assocaro=266486781</pickID>
          <phase>P</phase>
          <timeCorrection>-0.13</timeCorrection>
          <azimuth>259.0</azimuth>
          <distance>0.3592</distance>
          <takeoffAngle>
            <value>97.0</value>
          </takeoffAngle>
          <timeResidual>0.17</timeResidual>
          <timeWeight>0.15</timeWeight>
          <creationInfo>
            <agencyID>CI</agencyID>
            <creationTime>2025-01-19T02:17:12.000000Z</creationTime>
          </creationInfo>
        </arrival>
        <arrival publicID="quakeml:service.scedc.caltech.edu/fdsnws/event/1/query?assocaro=266486789">
          <pickID>quakeml:service.scedc.caltech.edu/fdsnws/event/1/query?assocaro=266486789</pickID>
          <phase>P</phase>
          <timeCorrection>-0.17</timeCorrection>
          <azimuth>300.0</azimuth>
          <distance>0.3814</distance>
          <takeoffAngle>
            <value>96.0</value>
          </takeoffAngle>
          <timeResidual>-0.08</timeResidual>
          <timeWeight>0.1</timeWeight>
          <creationInfo>
            <agencyID>CI</agencyID>
            <creationTime>2025-01-19T02:17:12.000000Z</creationTime>
          </creationInfo>
        </arrival>
        <arrival publicID="quakeml:service.scedc.caltech.edu/fdsnws/event/1/query?assocaro=266486797">
          <pickID>quakeml:service.scedc.caltech.edu/fdsnws/event/1/query?assocaro=266486797</pickID>
          <phase>S</phase>
          <timeCorrection>-0.43</timeCorrection>
          <azimuth>300.0</azimuth>
          <distance>0.3814</distance>
          <takeoffAngle>
            <value>96.0</value>
          </takeoffAngle>
          <timeResidual>-0.16</timeResidual>
          <timeWeight>0.05</timeWeight>
          <creationInfo>
            <agencyID>CI</agencyID>
            <creationTime>2025-01-19T02:17:12.000000Z</creationTime>
          </creationInfo>
        </arrival>
        <arrival publicID="quakeml:service.scedc.caltech.edu/fdsnws/event/1/query?assocaro=266486805">
          <pickID>quakeml:service.scedc.caltech.edu/fdsnws/event/1/query?assocaro=266486805</pickID>
          <phase>P</phase>
          <timeCorrection>0.0</timeCorrection>
          <azimuth>182.0</azimuth>
          <distance>0.5552</distance>
          <takeoffAngle>
            <value>93.0</value>
          </takeoffAngle>
          <timeResidual>-0.32</timeResidual>
          <timeWeight>0.1</timeWeight>
          <creationInfo>
            <agencyID>CI</agencyID>
            <creationTime>2025-01-19T02:17:12.000000Z</creationTime>
          </creationInfo>
        </arrival>
        <arrival publicID="quakeml:service.scedc.caltech.edu/fdsnws/event/1/query?assocaro=266486813">
          <pickID>quakeml:service.scedc.caltech.edu/fdsnws/event/1/query?assocaro=266486813</pickID>
          <phase>S</phase>
          <timeCorrection>0.0</timeCorrection>
          <azimuth>182.0</azimuth>
          <distance>0.5552</distance>
          <takeoffAngle>
            <value>93.0</value>
          </takeoffAngle>
          <timeResidual>-0.35</timeResidual>
          <timeWeight>0.03</timeWeight>
          <creationInfo>
            <agencyID>CI</agencyID>
            <creationTime>2025-01-19T02:17:12.000000Z</creationTime>
          </creationInfo>
        </arrival>
      </origin>
      <magnitude publicID="quakeml:service.scedc.caltech.edu/fdsnws/event/1/query?magnitudeid=109268453">
        <mag>
          <value>0.1</value>
          <uncertainty>0.059</uncertainty>
        </mag>
        <type>Ml</type>
        <originID>quakeml:service.scedc.caltech.edu/fdsnws/event/1/query?originid=105812069</originID>
        <methodID>smi:ci.anss.org/magnitude/CISNml2</methodID>
        <stationCount>5</stationCount>
        <azimuthalGap>154.9</azimuthalGap>
        <evaluationMode>automatic</evaluationMode>
        <evaluationStatus>preliminary</evaluationStatus>
        <stationMagnitudeContribution>
          <stationMagnitudeID>quakeml:service.scedc.caltech.edu/fdsnws/event/1/query?assocammid=930514429</stationMagnitudeID>
          <weight>1.0</weight>
          <residual>-0.16</residual>
        </stationMagnitudeContribution>
        <stationMagnitudeContribution>
          <stationMagnitudeID>quakeml:service.scedc.caltech.edu/fdsnws/event/1/query?assocammid=930514501</stationMagnitudeID>
          <weight>0.0</weight>
          <residual>0.59</residual>
        </stationMagnitudeContribution>
        <stationMagnitudeContribution>
          <stationMagnitudeID>quakeml:service.scedc.caltech.edu/fdsnws/event/1/query?assocammid=930514541</stationMagnitudeID>
          <weight>0.0</weight>
          <residual>0.59</residual>
        </stationMagnitudeContribution>
        <stationMagnitudeContribution>
          <stationMagnitudeID>quakeml:service.scedc.caltech.edu/fdsnws/event/1/query?assocammid=930514413</stationMagnitudeID>
          <weight>1.0</weight>
          <residual>0.06</residual>
        </stationMagnitudeContribution>
        <stationMagnitudeContribution>
          <stationMagnitudeID>quakeml:service.scedc.caltech.edu/fdsnws/event/1/query?assocammid=930514581</stationMagnitudeID>
          <weight>0.0</weight>
          <residual>1.58</residual>
        </stationMagnitudeContribution>
        <stationMagnitudeContribution>
          <stationMagnitudeID>quakeml:service.scedc.caltech.edu/fdsnws/event/1/query?assocammid=930514437</stationMagnitudeID>
          <weight>1.0</weight>
          <residual>0.0</residual>
        </stationMagnitudeContribution>
        <stationMagnitudeContribution>
          <stationMagnitudeID>quakeml:service.scedc.caltech.edu/fdsnws/event/1/query?assocammid=930514525</stationMagnitudeID>
          <weight>0.0</weight>
          <residual>0.49</residual>
        </stationMagnitudeContribution>
        <stationMagnitudeContribution>
          <stationMagnitudeID>quakeml:service.scedc.caltech.edu/fdsnws/event/1/query?assocammid=930514613</stationMagnitudeID>
          <weight>0.0</weight>
          <residual>1.28</residual>
        </stationMagnitudeContribution>
        <stationMagnitudeContribution>
          <stationMagnitudeID>quakeml:service.scedc.caltech.edu/fdsnws/event/1/query?assocammid=930514469</stationMagnitudeID>
          <weight>0.0</weight>
          <residual>0.72</residual>
        </stationMagnitudeContribution>
        <stationMagnitudeContribution>
          <stationMagnitudeID>quakeml:service.scedc.caltech.edu/fdsnws/event/1/query?assocammid=930514549</stationMagnitudeID>
          <weight>0.0</weight>
          <residual>0.67</residual>
        </stationMagnitudeContribution>
        <stationMagnitudeContribution>
          <stationMagnitudeID>quakeml:service.scedc.caltech.edu/fdsnws/event/1/query?assocammid=930514493</stationMagnitudeID>
          <weight>0.0</weight>
          <residual>0.52</residual>
        </stationMagnitudeContribution>
        <stationMagnitudeContribution>
          <stationMagnitudeID>quakeml:service.scedc.caltech.edu/fdsnws/event/1/query?assocammid=930514573</stationMagnitudeID>
          <weight>0.0</weight>
          <residual>0.59</residual>
        </stationMagnitudeContribution>
        <stationMagnitudeContribution>
          <stationMagnitudeID>quakeml:service.scedc.caltech.edu/fdsnws/event/1/query?assocammid=930514565</stationMagnitudeID>
          <weight>0.0</weight>
          <residual>0.54</residual>
        </stationMagnitudeContribution>
        <stationMagnitudeContribution>
          <stationMagnitudeID>quakeml:service.scedc.caltech.edu/fdsnws/event/1/query?assocammid=930514477</stationMagnitudeID>
          <weight>1.0</weight>
          <residual>0.49</residual>
        </stationMagnitudeContribution>
        <stationMagnitudeContribution>
          <stationMagnitudeID>quakeml:service.scedc.caltech.edu/fdsnws/event/1/query?assocammid=930514461</stationMagnitudeID>
          <weight>1.0</weight>
          <residual>0.0</residual>
        </stationMagnitudeContribution>
        <stationMagnitudeContribution>
          <stationMagnitudeID>quakeml:service.scedc.caltech.edu/fdsnws/event/1/query?assocammid=930514485</stationMagnitudeID>
          <weight>0.0</weight>
          <residual>0.05</residual>
        </stationMagnitudeContribution>
        <stationMagnitudeContribution>
          <stationMagnitudeID>quakeml:service.scedc.caltech.edu/fdsnws/event/1/query?assocammid=930514605</stationMagnitudeID>
          <weight>0.0</weight>
          <residual>2.1</residual>
        </stationMagnitudeContribution>
        <stationMagnitudeContribution>
          <stationMagnitudeID>quakeml:service.scedc.caltech.edu/fdsnws/event/1/query?assocammid=930514589</stationMagnitudeID>
          <weight>0.0</weight>
          <residual>1.87</residual>
        </stationMagnitudeContribution>
        <stationMagnitudeContribution>
          <stationMagnitudeID>quakeml:service.scedc.caltech.edu/fdsnws/event/1/query?assocammid=930514445</stationMagnitudeID>
          <weight>1.0</weight>
          <residual>-0.04</residual>
        </stationMagnitudeContribution>
        <stationMagnitudeContribution>
          <stationMagnitudeID>quakeml:service.scedc.caltech.edu/fdsnws/event/1/query?assocammid=930514557</stationMagnitudeID>
          <weight>0.0</weight>
          <residual>1.27</residual>
        </stationMagnitudeContribution>
        <stationMagnitudeContribution>
          <stationMagnitudeID>quakeml:service.scedc.caltech.edu/fdsnws/event/1/query?assocammid=930514453</stationMagnitudeID>
          <weight>1.0</weight>
          <residual>0.15</residual>
        </stationMagnitudeContribution>
        <stationMagnitudeContribution>
          <stationMagnitudeID>quakeml:service.scedc.caltech.edu/fdsnws/event/1/query?assocammid=930514405</stationMagnitudeID>
          <weight>1.0</weight>
          <residual>0.13</residual>
        </stationMagnitudeContribution>
        <stationMagnitudeContribution>
          <stationMagnitudeID>quakeml:service.scedc.caltech.edu/fdsnws/event/1/query?assocammid=930514421</stationMagnitudeID>
          <weight>1.0</weight>
          <residual>-0.01</residual>
        </stationMagnitudeContribution>
        <stationMagnitudeContribution>
          <stationMagnitudeID>quakeml:service.scedc.caltech.edu/fdsnws/event/1/query?assocammid=930514597</stationMagnitudeID>
          <weight>0.0</weight>
          <residual>1.67</residual>
        </stationMagnitudeContribution>
        <stationMagnitudeContribution>
          <stationMagnitudeID>quakeml:service.scedc.caltech.edu/fdsnws/event/1/query?assocammid=930514533</stationMagnitudeID>
          <weight>0.0</weight>
          <residual>0.56</residual>
        </stationMagnitudeContribution>
        <stationMagnitudeContribution>
          <stationMagnitudeID>quakeml:service.scedc.caltech.edu/fdsnws/event/1/query?assocammid=930514509</stationMagnitudeID>
          <weight>0.0</weight>
          <residual>0.18</residual>
        </stationMagnitudeContribution>
        <stationMagnitudeContribution>
          <stationMagnitudeID>quakeml:service.scedc.caltech.edu/fdsnws/event/1/query?assocammid=930514517</stationMagnitudeID>
          <weight>0.0</weight>
          <residual>0.36</residual>
        </stationMagnitudeContribution>
        <creationInfo>
          <agencyID>CI</agencyID>
          <creationTime>2025-01-19T02:17:20.000000Z</creationTime>
        </creationInfo>
      </magnitude>
      <stationMagnitude publicID="quakeml:service.scedc.caltech.edu/fdsnws/event/1/query?assocammid=930514405">
        <originID>quakeml:service.scedc.caltech.edu/fdsnws/event/1/query?originid=105812069</originID>
        <mag>
          <value>0.23</value>
        </mag>
        <type>ML</type>
        <amplitudeID>quakeml:service.scedc.caltech.edu/fdsnws/event/1/query?ampid=930514405</amplitudeID>
        <waveformID networkCode="AZ" stationCode="FRD" locationCode="" channelCode="HHN"></waveformID>
      </stationMagnitude>
      <stationMagnitude publicID="quakeml:service.scedc.caltech.edu/fdsnws/event/1/query?assocammid=930514413">
        <originID>quakeml:service.scedc.caltech.edu/fdsnws/event/1/query?originid=105812069</originID>
        <mag>
          <value>0.16</value>
        </mag>
        <type>ML</type>
        <amplitudeID>quakeml:service.scedc.caltech.edu/fdsnws/event/1/query?ampid=930514413</amplitudeID>
        <waveformID networkCode="AZ" stationCode="FRD" locationCode="" channelCode="HHE"></waveformID>
      </stationMagnitude>
      <stationMagnitude publicID="quakeml:service.scedc.caltech.edu/fdsnws/event/1/query?assocammid=930514421">
        <originID>quakeml:service.scedc.caltech.edu/fdsnws/event/1/query?originid=105812069</originID>
        <mag>
          <value>0.09</value>
        </mag>
        <type>ML</type>
        <amplitudeID>quakeml:service.scedc.caltech.edu/fdsnws/event/1/query?ampid=930514421</amplitudeID>
        <waveformID networkCode="AZ" stationCode="SND" locationCode="" channelCode="HHN"></waveformID>
      </stationMagnitude>
      <stationMagnitude publicID="quakeml:service.scedc.caltech.edu/fdsnws/event/1/query?assocammid=930514429">
        <originID>quakeml:service.scedc.caltech.edu/fdsnws/event/1/query?originid=105812069</originID>
        <mag>
          <value>-0.06</value>
        </mag>
        <type>ML</type>
        <amplitudeID>quakeml:service.scedc.caltech.edu/fdsnws/event/1/query?ampid=930514429</amplitudeID>
        <waveformID networkCode="AZ" stationCode="SND" locationCode="" channelCode="HHE"></waveformID>
      </stationMagnitude>
      <stationMagnitude publicID="quakeml:service.scedc.caltech.edu/fdsnws/event/1/query?assocammid=930514437">
        <originID>quakeml:service.scedc.caltech.edu/fdsnws/event/1/query?originid=105812069</originID>
        <mag>
          <value>0.1</value>
        </mag>
        <type>ML</type>
        <amplitudeID>quakeml:service.scedc.caltech.edu/fdsnws/event/1/query?ampid=930514437</amplitudeID>
        <waveformID networkCode="CI" stationCode="DNR" locationCode="" channelCode="HHN"></waveformID>
      </stationMagnitude>
      <stationMagnitude publicID="quakeml:service.scedc.caltech.edu/fdsnws/event/1/query?assocammid=930514445">
        <originID>quakeml:service.scedc.caltech.edu/fdsnws/event/1/query?originid=105812069</originID>
        <mag>
          <value>0.06</value>
        </mag>
        <type>ML</type>
        <amplitudeID>quakeml:service.scedc.caltech.edu/fdsnws/event/1/query?ampid=930514445</amplitudeID>
        <waveformID networkCode="CI" stationCode="DNR" locationCode="" channelCode="HHE"></waveformID>
      </stationMagnitude>
      <stationMagnitude publicID="quakeml:service.scedc.caltech.edu/fdsnws/event/1/query?assocammid=930514453">
        <originID>quakeml:service.scedc.caltech.edu/fdsnws/event/1/query?originid=105812069</originID>
        <mag>
          <value>0.25</value>
        </mag>
        <type>ML</type>
        <amplitudeID>quakeml:service.scedc.caltech.edu/fdsnws/event/1/query?ampid=930514453</amplitudeID>
        <waveformID networkCode="AZ" stationCode="LVA2" locationCode="" channelCode="HHN"></waveformID>
      </stationMagnitude>
      <stationMagnitude publicID="quakeml:service.scedc.caltech.edu/fdsnws/event/1/query?assocammid=930514461">
        <originID>quakeml:service.scedc.caltech.edu/fdsnws/event/1/query?originid=105812069</originID>
        <mag>
          <value>0.1</value>
        </mag>
        <type>ML</type>
        <amplitudeID>quakeml:service.scedc.caltech.edu/fdsnws/event/1/query?ampid=930514461</amplitudeID>
        <waveformID networkCode="AZ" stationCode="LVA2" locationCode="" channelCode="HHE"></waveformID>
      </stationMagnitude>
      <stationMagnitude publicID="quakeml:service.scedc.caltech.edu/fdsnws/event/1/query?assocammid=930514469">
        <originID>quakeml:service.scedc.caltech.edu/fdsnws/event/1/query?originid=105812069</originID>
        <mag>
          <value>0.82</value>
        </mag>
        <type>ML</type>
        <amplitudeID>quakeml:service.scedc.caltech.edu/fdsnws/event/1/query?ampid=930514469</amplitudeID>
        <waveformID networkCode="AZ" stationCode="CRY" locationCode="" channelCode="HHN"></waveformID>
      </stationMagnitude>
      <stationMagnitude publicID="quakeml:service.scedc.caltech.edu/fdsnws/event/1/query?assocammid=930514477">
        <originID>quakeml:service.scedc.caltech.edu/fdsnws/event/1/query?originid=105812069</originID>
        <mag>
          <value>0.59</value>
        </mag>
        <type>ML</type>
        <amplitudeID>quakeml:service.scedc.caltech.edu/fdsnws/event/1/query?ampid=930514477</amplitudeID>
        <waveformID networkCode="AZ" stationCode="CRY" locationCode="" channelCode="HHE"></waveformID>
      </stationMagnitude>
      <stationMagnitude publicID="quakeml:service.scedc.caltech.edu/fdsnws/event/1/query?assocammid=930514485">
        <originID>quakeml:service.scedc.caltech.edu/fdsnws/event/1/query?originid=105812069</originID>
        <mag>
          <value>0.15</value>
        </mag>
        <type>ML</type>
        <amplitudeID>quakeml:service.scedc.caltech.edu/fdsnws/event/1/query?ampid=930514485</amplitudeID>
        <waveformID networkCode="CI" stationCode="CSH" locationCode="" channelCode="HHE"></waveformID>
      </stationMagnitude>
      <stationMagnitude publicID="quakeml:service.scedc.caltech.edu/fdsnws/event/1/query?assocammid=930514493">
        <originID>quakeml:service.scedc.caltech.edu/fdsnws/event/1/query?originid=105812069</originID>
        <mag>
          <value>0.62</value>
        </mag>
        <type>ML</type>
        <amplitudeID>quakeml:service.scedc.caltech.edu/fdsnws/event/1/query?ampid=930514493</amplitudeID>
        <waveformID networkCode="AZ" stationCode="PFO" locationCode="" channelCode="HHN"></waveformID>
      </stationMagnitude>
      <stationMagnitude publicID="quakeml:service.scedc.caltech.edu/fdsnws/event/1/query?assocammid=930514501">
        <originID>quakeml:service.scedc.caltech.edu/fdsnws/event/1/query?originid=105812069</originID>
        <mag>
          <value>0.69</value>
        </mag>
        <type>ML</type>
        <amplitudeID>quakeml:service.scedc.caltech.edu/fdsnws/event/1/query?ampid=930514501</amplitudeID>
        <waveformID networkCode="AZ" stationCode="PFO" locationCode="" channelCode="HHE"></waveformID>
      </stationMagnitude>
      <stationMagnitude publicID="quakeml:service.scedc.caltech.edu/fdsnws/event/1/query?assocammid=930514509">
        <originID>quakeml:service.scedc.caltech.edu/fdsnws/event/1/query?originid=105812069</originID>
        <mag>
          <value>0.28</value>
        </mag>
        <type>ML</type>
        <amplitudeID>quakeml:service.scedc.caltech.edu/fdsnws/event/1/query?ampid=930514509</amplitudeID>
        <waveformID networkCode="CI" stationCode="PLM" locationCode="" channelCode="HHN"></waveformID>
      </stationMagnitude>
      <stationMagnitude publicID="quakeml:service.scedc.caltech.edu/fdsnws/event/1/query?assocammid=930514517">
        <originID>quakeml:service.scedc.caltech.edu/fdsnws/event/1/query?originid=105812069</originID>
        <mag>
          <value>0.46</value>
        </mag>
        <type>ML</type>
        <amplitudeID>quakeml:service.scedc.caltech.edu/fdsnws/event/1/query?ampid=930514517</amplitudeID>
        <waveformID networkCode="CI" stationCode="PLM" locationCode="" channelCode="HHE"></waveformID>
      </stationMagnitude>
      <stationMagnitude publicID="quakeml:service.scedc.caltech.edu/fdsnws/event/1/query?assocammid=930514525">
        <originID>quakeml:service.scedc.caltech.edu/fdsnws/event/1/query?originid=105812069</originID>
        <mag>
          <value>0.59</value>
        </mag>
        <type>ML</type>
        <amplitudeID>quakeml:service.scedc.caltech.edu/fdsnws/event/1/query?ampid=930514525</amplitudeID>
        <waveformID networkCode="CI" stationCode="BOR" locationCode="" channelCode="HHN"></waveformID>
      </stationMagnitude>
      <stationMagnitude publicID="quakeml:service.scedc.caltech.edu/fdsnws/event/1/query?assocammid=930514533">
        <originID>quakeml:service.scedc.caltech.edu/fdsnws/event/1/query?originid=105812069</originID>
        <mag>
          <value>0.66</value>
        </mag>
        <type>ML</type>
        <amplitudeID>quakeml:service.scedc.caltech.edu/fdsnws/event/1/query?ampid=930514533</amplitudeID>
        <waveformID networkCode="CI" stationCode="BOR" locationCode="" channelCode="HHE"></waveformID>
      </stationMagnitude>
      <stationMagnitude publicID="quakeml:service.scedc.caltech.edu/fdsnws/event/1/query?assocammid=930514541">
        <originID>quakeml:service.scedc.caltech.edu/fdsnws/event/1/query?originid=105812069</originID>
        <mag>
          <value>0.69</value>
        </mag>
        <type>ML</type>
        <amplitudeID>quakeml:service.scedc.caltech.edu/fdsnws/event/1/query?ampid=930514541</amplitudeID>
        <waveformID networkCode="AZ" stationCode="RDM" locationCode="" channelCode="HHN"></waveformID>
      </stationMagnitude>
      <stationMagnitude publicID="quakeml:service.scedc.caltech.edu/fdsnws/event/1/query?assocammid=930514549">
        <originID>quakeml:service.scedc.caltech.edu/fdsnws/event/1/query?originid=105812069</originID>
        <mag>
          <value>0.77</value>
        </mag>
        <type>ML</type>
        <amplitudeID>quakeml:service.scedc.caltech.edu/fdsnws/event/1/query?ampid=930514549</amplitudeID>
        <waveformID networkCode="AZ" stationCode="RDM" locationCode="" channelCode="HHE"></waveformID>
      </stationMagnitude>
      <stationMagnitude publicID="quakeml:service.scedc.caltech.edu/fdsnws/event/1/query?assocammid=930514557">
        <originID>quakeml:service.scedc.caltech.edu/fdsnws/event/1/query?originid=105812069</originID>
        <mag>
          <value>1.37</value>
        </mag>
        <type>ML</type>
        <amplitudeID>quakeml:service.scedc.caltech.edu/fdsnws/event/1/query?ampid=930514557</amplitudeID>
        <waveformID networkCode="CI" stationCode="PSD" locationCode="" channelCode="HHE"></waveformID>
      </stationMagnitude>
      <stationMagnitude publicID="quakeml:service.scedc.caltech.edu/fdsnws/event/1/query?assocammid=930514565">
        <originID>quakeml:service.scedc.caltech.edu/fdsnws/event/1/query?originid=105812069</originID>
        <mag>
          <value>0.64</value>
        </mag>
        <type>ML</type>
        <amplitudeID>quakeml:service.scedc.caltech.edu/fdsnws/event/1/query?ampid=930514565</amplitudeID>
        <waveformID networkCode="CI" stationCode="SLR" locationCode="" channelCode="HHN"></waveformID>
      </stationMagnitude>
      <stationMagnitude publicID="quakeml:service.scedc.caltech.edu/fdsnws/event/1/query?assocammid=930514573">
        <originID>quakeml:service.scedc.caltech.edu/fdsnws/event/1/query?originid=105812069</originID>
        <mag>
          <value>0.69</value>
        </mag>
        <type>ML</type>
        <amplitudeID>quakeml:service.scedc.caltech.edu/fdsnws/event/1/query?ampid=930514573</amplitudeID>
        <waveformID networkCode="CI" stationCode="SLR" locationCode="" channelCode="HHE"></waveformID>
      </stationMagnitude>
      <stationMagnitude publicID="quakeml:service.scedc.caltech.edu/fdsnws/event/1/query?assocammid=930514581">
        <originID>quakeml:service.scedc.caltech.edu/fdsnws/event/1/query?originid=105812069</originID>
        <mag>
          <value>1.68</value>
        </mag>
        <type>ML</type>
        <amplitudeID>quakeml:service.scedc.caltech.edu/fdsnws/event/1/query?ampid=930514581</amplitudeID>
        <waveformID networkCode="CI" stationCode="CZN" locationCode="" channelCode="HHE"></waveformID>
      </stationMagnitude>
      <stationMagnitude publicID="quakeml:service.scedc.caltech.edu/fdsnws/event/1/query?assocammid=930514589">
        <originID>quakeml:service.scedc.caltech.edu/fdsnws/event/1/query?originid=105812069</originID>
        <mag>
          <value>1.97</value>
        </mag>
        <type>ML</type>
        <amplitudeID>quakeml:service.scedc.caltech.edu/fdsnws/event/1/query?ampid=930514589</amplitudeID>
        <waveformID networkCode="CI" stationCode="CZN" locationCode="" channelCode="HNN"></waveformID>
      </stationMagnitude>
      <stationMagnitude publicID="quakeml:service.scedc.caltech.edu/fdsnws/event/1/query?assocammid=930514597">
        <originID>quakeml:service.scedc.caltech.edu/fdsnws/event/1/query?originid=105812069</originID>
        <mag>
          <value>1.77</value>
        </mag>
        <type>ML</type>
        <amplitudeID>quakeml:service.scedc.caltech.edu/fdsnws/event/1/query?ampid=930514597</amplitudeID>
        <waveformID networkCode="CI" stationCode="ESI2" locationCode="" channelCode="HHE"></waveformID>
      </stationMagnitude>
      <stationMagnitude publicID="quakeml:service.scedc.caltech.edu/fdsnws/event/1/query?assocammid=930514605">
        <originID>quakeml:service.scedc.caltech.edu/fdsnws/event/1/query?originid=105812069</originID>
        <mag>
          <value>2.2</value>
        </mag>
        <type>ML</type>
        <amplitudeID>quakeml:service.scedc.caltech.edu/fdsnws/event/1/query?ampid=930514605</amplitudeID>
        <waveformID networkCode="CE" stationCode="13141" locationCode="10" channelCode="HNE"></waveformID>
      </stationMagnitude>
      <stationMagnitude publicID="quakeml:service.scedc.caltech.edu/fdsnws/event/1/query?assocammid=930514613">
        <originID>quakeml:service.scedc.caltech.edu/fdsnws/event/1/query?originid=105812069</originID>
        <mag>
          <value>1.38</value>
        </mag>
        <type>ML</type>
        <amplitudeID>quakeml:service.scedc.caltech.edu/fdsnws/event/1/query?ampid=930514613</amplitudeID>
        <waveformID networkCode="CI" stationCode="BOM" locationCode="" channelCode="HHE"></waveformID>
      </stationMagnitude>
      <pick publicID="quakeml:service.scedc.caltech.edu/fdsnws/event/1/query?assocaro=144699375">
        <time>
          <value>2025-01-19T02:14:01.420000Z</value>
          <uncertainty>0.06</uncertainty>
        </time>
        <waveformID networkCode="CI" stationCode="CLT" locationCode="" channelCode="HNN"></waveformID>
        <phaseHint>S</phaseHint>
        <polarity>undecidable</polarity>
        <evaluationMode>automatic</evaluationMode>
        <evaluationStatus>preliminary</evaluationStatus>
        <creationInfo>
          <agencyID>CI</agencyID>
          <creationTime>2025-01-19T02:14:43.000000Z</creationTime>
        </creationInfo>
      </pick>
      <pick publicID="quakeml:service.scedc.caltech.edu/fdsnws/event/1/query?assocaro=266486549">
        <time>
          <value>2025-01-19T02:13:35.480000Z</value>
          <uncertainty>0.03</uncertainty>
        </time>
        <waveformID networkCode="AZ" stationCode="FRD" locationCode="" channelCode="HHZ"></waveformID>
        <onset>impulsive</onset>
        <phaseHint>P</phaseHint>
        <polarity>undecidable</polarity>
        <evaluationMode>automatic</evaluationMode>
        <evaluationStatus>preliminary</evaluationStatus>
        <creationInfo>
          <agencyID>CI</agencyID>
          <creationTime>2025-01-19T02:17:12.000000Z</creationTime>
        </creationInfo>
      </pick>
      <pick publicID="quakeml:service.scedc.caltech.edu/fdsnws/event/1/query?assocaro=266486557">
        <time>
          <value>2025-01-19T02:13:36.790000Z</value>
          <uncertainty>0.06</uncertainty>
        </time>
        <waveformID networkCode="AZ" stationCode="FRD" locationCode="" channelCode="HHE"></waveformID>
        <onset>impulsive</onset>
        <phaseHint>S</phaseHint>
        <polarity>undecidable</polarity>
        <evaluationMode>automatic</evaluationMode>
        <evaluationStatus>preliminary</evaluationStatus>
        <creationInfo>
          <agencyID>CI</agencyID>
          <creationTime>2025-01-19T02:17:12.000000Z</creationTime>
        </creationInfo>
      </pick>
      <pick publicID="quakeml:service.scedc.caltech.edu/fdsnws/event/1/query?assocaro=266486565">
        <time>
          <value>2025-01-19T02:13:36.150000Z</value>
          <uncertainty>0.15</uncertainty>
        </time>
        <waveformID networkCode="AZ" stationCode="SND" locationCode="" channelCode="HHZ"></waveformID>
        <onset>emergent</onset>
        <phaseHint>P</phaseHint>
        <polarity>undecidable</polarity>
        <evaluationMode>automatic</evaluationMode>
        <evaluationStatus>preliminary</evaluationStatus>
        <creationInfo>
          <agencyID>CI</agencyID>
          <creationTime>2025-01-19T02:17:12.000000Z</creationTime>
        </creationInfo>
      </pick>
      <pick publicID="quakeml:service.scedc.caltech.edu/fdsnws/event/1/query?assocaro=266486573">
        <time>
          <value>2025-01-19T02:13:36.340000Z</value>
          <uncertainty>0.15</uncertainty>
        </time>
        <waveformID networkCode="CI" stationCode="DNR" locationCode="" channelCode="HHZ"></waveformID>
        <onset>emergent</onset>
        <phaseHint>P</phaseHint>
        <polarity>undecidable</polarity>
        <evaluationMode>automatic</evaluationMode>
        <evaluationStatus>preliminary</evaluationStatus>
        <creationInfo>
          <agencyID>CI</agencyID>
          <creationTime>2025-01-19T02:17:12.000000Z</creationTime>
        </creationInfo>
      </pick>
      <pick publicID="quakeml:service.scedc.caltech.edu/fdsnws/event/1/query?assocaro=266486581">
        <time>
          <value>2025-01-19T02:13:38.700000Z</value>
          <uncertainty>0.15</uncertainty>
        </time>
        <waveformID networkCode="CI" stationCode="DNR" locationCode="" channelCode="HHE"></waveformID>
        <onset>emergent</onset>
        <phaseHint>S</phaseHint>
        <polarity>undecidable</polarity>
        <evaluationMode>automatic</evaluationMode>
        <evaluationStatus>preliminary</evaluationStatus>
        <creationInfo>
          <agencyID>CI</agencyID>
          <creationTime>2025-01-19T02:17:12.000000Z</creationTime>
        </creationInfo>
      </pick>
      <pick publicID="quakeml:service.scedc.caltech.edu/fdsnws/event/1/query?assocaro=266486589">
        <time>
          <value>2025-01-19T02:13:36.530000Z</value>
          <uncertainty>0.03</uncertainty>
        </time>
        <waveformID networkCode="AZ" stationCode="LVA2" locationCode="" channelCode="HHZ"></waveformID>
        <onset>impulsive</onset>
        <phaseHint>P</phaseHint>
        <polarity>negative</polarity>
        <evaluationMode>automatic</evaluationMode>
        <evaluationStatus>preliminary</evaluationStatus>
        <creationInfo>
          <agencyID>CI</agencyID>
          <creationTime>2025-01-19T02:17:12.000000Z</creationTime>
        </creationInfo>
      </pick>
      <pick publicID="quakeml:service.scedc.caltech.edu/fdsnws/event/1/query?assocaro=266486597">
        <time>
          <value>2025-01-19T02:13:38.660000Z</value>
          <uncertainty>0.15</uncertainty>
        </time>
        <waveformID networkCode="AZ" stationCode="LVA2" locationCode="" channelCode="HHE"></waveformID>
        <onset>emergent</onset>
        <phaseHint>S</phaseHint>
        <polarity>undecidable</polarity>
        <evaluationMode>automatic</evaluationMode>
        <evaluationStatus>preliminary</evaluationStatus>
        <creationInfo>
          <agencyID>CI</agencyID>
          <creationTime>2025-01-19T02:17:12.000000Z</creationTime>
        </creationInfo>
      </pick>
      <pick publicID="quakeml:service.scedc.caltech.edu/fdsnws/event/1/query?assocaro=266486605">
        <time>
          <value>2025-01-19T02:13:39.280000Z</value>
          <uncertainty>0.15</uncertainty>
        </time>
        <waveformID networkCode="AZ" stationCode="CRY" locationCode="" channelCode="HHE"></waveformID>
        <onset>emergent</onset>
        <phaseHint>S</phaseHint>
        <polarity>undecidable</polarity>
        <evaluationMode>automatic</evaluationMode>
        <evaluationStatus>preliminary</evaluationStatus>
        <creationInfo>
          <agencyID>CI</agencyID>
          <creationTime>2025-01-19T02:17:12.000000Z</creationTime>
        </creationInfo>
      </pick>
      <pick publicID="quakeml:service.scedc.caltech.edu/fdsnws/event/1/query?assocaro=266486613">
        <time>
          <value>2025-01-19T02:13:37.220000Z</value>
          <uncertainty>0.03</uncertainty>
        </time>
        <waveformID networkCode="CI" stationCode="ANG" locationCode="" channelCode="HHZ"></waveformID>
        <onset>impulsive</onset>
        <phaseHint>P</phaseHint>
        <polarity>positive</polarity>
        <evaluationMode>automatic</evaluationMode>
        <evaluationStatus>preliminary</evaluationStatus>
        <creationInfo>
          <agencyID>CI</agencyID>
          <creationTime>2025-01-19T02:17:12.000000Z</creationTime>
        </creationInfo>
      </pick>
      <pick publicID="quakeml:service.scedc.caltech.edu/fdsnws/event/1/query?assocaro=266486621">
        <time>
          <value>2025-01-19T02:13:39.820000Z</value>
          <uncertainty>0.15</uncertainty>
        </time>
        <waveformID networkCode="CI" stationCode="ANG" locationCode="" channelCode="HHE"></waveformID>
        <onset>emergent</onset>
        <phaseHint>S</phaseHint>
        <polarity>undecidable</polarity>
        <evaluationMode>automatic</evaluationMode>
        <evaluationStatus>preliminary</evaluationStatus>
        <creationInfo>
          <agencyID>CI</agencyID>
          <creationTime>2025-01-19T02:17:12.000000Z</creationTime>
        </creationInfo>
      </pick>
      <pick publicID="quakeml:service.scedc.caltech.edu/fdsnws/event/1/query?assocaro=266486629">
        <time>
          <value>2025-01-19T02:13:37.420000Z</value>
          <uncertainty>0.03</uncertainty>
        </time>
        <waveformID networkCode="CI" stationCode="CSH" locationCode="" channelCode="HHZ"></waveformID>
        <onset>impulsive</onset>
        <phaseHint>P</phaseHint>
        <polarity>negative</polarity>
        <evaluationMode>automatic</evaluationMode>
        <evaluationStatus>preliminary</evaluationStatus>
        <creationInfo>
          <agencyID>CI</agencyID>
          <creationTime>2025-01-19T02:17:12.000000Z</creationTime>
        </creationInfo>
      </pick>
      <pick publicID="quakeml:service.scedc.caltech.edu/fdsnws/event/1/query?assocaro=266486637">
        <time>
          <value>2025-01-19T02:13:40.210000Z</value>
          <uncertainty>0.15</uncertainty>
        </time>
        <waveformID networkCode="CI" stationCode="CSH" locationCode="" channelCode="HHE"></waveformID>
        <onset>emergent</onset>
        <phaseHint>S</phaseHint>
        <polarity>undecidable</polarity>
        <evaluationMode>automatic</evaluationMode>
        <evaluationStatus>preliminary</evaluationStatus>
        <creationInfo>
          <agencyID>CI</agencyID>
          <creationTime>2025-01-19T02:17:12.000000Z</creationTime>
        </creationInfo>
      </pick>
      <pick publicID="quakeml:service.scedc.caltech.edu/fdsnws/event/1/query?assocaro=266486645">
        <time>
          <value>2025-01-19T02:13:37.690000Z</value>
          <uncertainty>0.03</uncertainty>
        </time>
        <waveformID networkCode="AZ" stationCode="PFO" locationCode="" channelCode="HHZ"></waveformID>
        <onset>impulsive</onset>
        <phaseHint>P</phaseHint>
        <polarity>negative</polarity>
        <evaluationMode>automatic</evaluationMode>
        <evaluationStatus>preliminary</evaluationStatus>
        <creationInfo>
          <agencyID>CI</agencyID>
          <creationTime>2025-01-19T02:17:12.000000Z</creationTime>
        </creationInfo>
      </pick>
      <pick publicID="quakeml:service.scedc.caltech.edu/fdsnws/event/1/query?assocaro=266486653">
        <time>
          <value>2025-01-19T02:13:40.560000Z</value>
          <uncertainty>0.06</uncertainty>
        </time>
        <waveformID networkCode="AZ" stationCode="PFO" locationCode="" channelCode="HHE"></waveformID>
        <onset>impulsive</onset>
        <phaseHint>S</phaseHint>
        <polarity>undecidable</polarity>
        <evaluationMode>automatic</evaluationMode>
        <evaluationStatus>preliminary</evaluationStatus>
        <creationInfo>
          <agencyID>CI</agencyID>
          <creationTime>2025-01-19T02:17:12.000000Z</creationTime>
        </creationInfo>
      </pick>
      <pick publicID="quakeml:service.scedc.caltech.edu/fdsnws/event/1/query?assocaro=266486661">
        <time>
          <value>2025-01-19T02:13:38.410000Z</value>
          <uncertainty>0.15</uncertainty>
        </time>
        <waveformID networkCode="CI" stationCode="PLM" locationCode="" channelCode="HHZ"></waveformID>
        <onset>emergent</onset>
        <phaseHint>P</phaseHint>
        <polarity>undecidable</polarity>
        <evaluationMode>automatic</evaluationMode>
        <evaluationStatus>preliminary</evaluationStatus>
        <creationInfo>
          <agencyID>CI</agencyID>
          <creationTime>2025-01-19T02:17:12.000000Z</creationTime>
        </creationInfo>
      </pick>
      <pick publicID="quakeml:service.scedc.caltech.edu/fdsnws/event/1/query?assocaro=266486669">
        <time>
          <value>2025-01-19T02:13:42.060000Z</value>
          <uncertainty>0.15</uncertainty>
        </time>
        <waveformID networkCode="CI" stationCode="PLM" locationCode="" channelCode="HHE"></waveformID>
        <onset>emergent</onset>
        <phaseHint>S</phaseHint>
        <polarity>undecidable</polarity>
        <evaluationMode>automatic</evaluationMode>
        <evaluationStatus>preliminary</evaluationStatus>
        <creationInfo>
          <agencyID>CI</agencyID>
          <creationTime>2025-01-19T02:17:12.000000Z</creationTime>
        </creationInfo>
      </pick>
      <pick publicID="quakeml:service.scedc.caltech.edu/fdsnws/event/1/query?assocaro=266486677">
        <time>
          <value>2025-01-19T02:13:42.040000Z</value>
          <uncertainty>0.15</uncertainty>
        </time>
        <waveformID networkCode="CI" stationCode="BOR" locationCode="" channelCode="HHE"></waveformID>
        <onset>emergent</onset>
        <phaseHint>S</phaseHint>
        <polarity>undecidable</polarity>
        <evaluationMode>automatic</evaluationMode>
        <evaluationStatus>preliminary</evaluationStatus>
        <creationInfo>
          <agencyID>CI</agencyID>
          <creationTime>2025-01-19T02:17:12.000000Z</creationTime>
        </creationInfo>
      </pick>
      <pick publicID="quakeml:service.scedc.caltech.edu/fdsnws/event/1/query?assocaro=266486685">
        <time>
          <value>2025-01-19T02:13:38.680000Z</value>
          <uncertainty>0.15</uncertainty>
        </time>
        <waveformID networkCode="AZ" stationCode="RDM" locationCode="" channelCode="BHZ"></waveformID>
        <onset>emergent</onset>
        <phaseHint>P</phaseHint>
        <polarity>undecidable</polarity>
        <evaluationMode>automatic</evaluationMode>
        <evaluationStatus>preliminary</evaluationStatus>
        <creationInfo>
          <agencyID>CI</agencyID>
          <creationTime>2025-01-19T02:17:12.000000Z</creationTime>
        </creationInfo>
      </pick>
      <pick publicID="quakeml:service.scedc.caltech.edu/fdsnws/event/1/query?assocaro=266486693">
        <time>
          <value>2025-01-19T02:13:42.250000Z</value>
          <uncertainty>0.15</uncertainty>
        </time>
        <waveformID networkCode="AZ" stationCode="RDM" locationCode="" channelCode="BHE"></waveformID>
        <onset>emergent</onset>
        <phaseHint>S</phaseHint>
        <polarity>undecidable</polarity>
        <evaluationMode>automatic</evaluationMode>
        <evaluationStatus>preliminary</evaluationStatus>
        <creationInfo>
          <agencyID>CI</agencyID>
          <creationTime>2025-01-19T02:17:12.000000Z</creationTime>
        </creationInfo>
      </pick>
      <pick publicID="quakeml:service.scedc.caltech.edu/fdsnws/event/1/query?assocaro=266486701">
        <time>
          <value>2025-01-19T02:13:38.770000Z</value>
          <uncertainty>0.03</uncertainty>
        </time>
        <waveformID networkCode="AZ" stationCode="KNW" locationCode="" channelCode="HHZ"></waveformID>
        <onset>impulsive</onset>
        <phaseHint>P</phaseHint>
        <polarity>undecidable</polarity>
        <evaluationMode>automatic</evaluationMode>
        <evaluationStatus>preliminary</evaluationStatus>
        <creationInfo>
          <agencyID>CI</agencyID>
          <creationTime>2025-01-19T02:17:12.000000Z</creationTime>
        </creationInfo>
      </pick>
      <pick publicID="quakeml:service.scedc.caltech.edu/fdsnws/event/1/query?assocaro=266486709">
        <time>
          <value>2025-01-19T02:13:42.440000Z</value>
          <uncertainty>0.06</uncertainty>
        </time>
        <waveformID networkCode="AZ" stationCode="KNW" locationCode="" channelCode="HHE"></waveformID>
        <onset>impulsive</onset>
        <phaseHint>S</phaseHint>
        <polarity>undecidable</polarity>
        <evaluationMode>automatic</evaluationMode>
        <evaluationStatus>preliminary</evaluationStatus>
        <creationInfo>
          <agencyID>CI</agencyID>
          <creationTime>2025-01-19T02:17:12.000000Z</creationTime>
        </creationInfo>
      </pick>
      <pick publicID="quakeml:service.scedc.caltech.edu/fdsnws/event/1/query?assocaro=266486717">
        <time>
          <value>2025-01-19T02:13:38.940000Z</value>
          <uncertainty>0.06</uncertainty>
        </time>
        <waveformID networkCode="CI" stationCode="MTG" locationCode="" channelCode="HHZ"></waveformID>
        <onset>impulsive</onset>
        <phaseHint>P</phaseHint>
        <polarity>positive</polarity>
        <evaluationMode>automatic</evaluationMode>
        <evaluationStatus>preliminary</evaluationStatus>
        <creationInfo>
          <agencyID>CI</agencyID>
          <creationTime>2025-01-19T02:17:12.000000Z</creationTime>
        </creationInfo>
      </pick>
      <pick publicID="quakeml:service.scedc.caltech.edu/fdsnws/event/1/query?assocaro=266486725">
        <time>
          <value>2025-01-19T02:13:42.750000Z</value>
          <uncertainty>0.15</uncertainty>
        </time>
        <waveformID networkCode="CI" stationCode="MTG" locationCode="" channelCode="HHE"></waveformID>
        <onset>emergent</onset>
        <phaseHint>S</phaseHint>
        <polarity>undecidable</polarity>
        <evaluationMode>automatic</evaluationMode>
        <evaluationStatus>preliminary</evaluationStatus>
        <creationInfo>
          <agencyID>CI</agencyID>
          <creationTime>2025-01-19T02:17:12.000000Z</creationTime>
        </creationInfo>
      </pick>
      <pick publicID="quakeml:service.scedc.caltech.edu/fdsnws/event/1/query?assocaro=266486733">
        <time>
          <value>2025-01-19T02:13:38.920000Z</value>
          <uncertainty>0.15</uncertainty>
        </time>
        <waveformID networkCode="CI" stationCode="PMD" locationCode="" channelCode="HHZ"></waveformID>
        <onset>emergent</onset>
        <phaseHint>P</phaseHint>
        <polarity>undecidable</polarity>
        <evaluationMode>automatic</evaluationMode>
        <evaluationStatus>preliminary</evaluationStatus>
        <creationInfo>
          <agencyID>CI</agencyID>
          <creationTime>2025-01-19T02:17:12.000000Z</creationTime>
        </creationInfo>
      </pick>
      <pick publicID="quakeml:service.scedc.caltech.edu/fdsnws/event/1/query?assocaro=266486741">
        <time>
          <value>2025-01-19T02:13:42.480000Z</value>
          <uncertainty>0.15</uncertainty>
        </time>
        <waveformID networkCode="CI" stationCode="PMD" locationCode="" channelCode="HHE"></waveformID>
        <onset>emergent</onset>
        <phaseHint>S</phaseHint>
        <polarity>undecidable</polarity>
        <evaluationMode>automatic</evaluationMode>
        <evaluationStatus>preliminary</evaluationStatus>
        <creationInfo>
          <agencyID>CI</agencyID>
          <creationTime>2025-01-19T02:17:12.000000Z</creationTime>
        </creationInfo>
      </pick>
      <pick publicID="quakeml:service.scedc.caltech.edu/fdsnws/event/1/query?assocaro=266486749">
        <time>
          <value>2025-01-19T02:13:39.010000Z</value>
          <uncertainty>0.06</uncertainty>
        </time>
        <waveformID networkCode="CI" stationCode="RCR" locationCode="" channelCode="HHZ"></waveformID>
        <onset>impulsive</onset>
        <phaseHint>P</phaseHint>
        <polarity>positive</polarity>
        <evaluationMode>automatic</evaluationMode>
        <evaluationStatus>preliminary</evaluationStatus>
        <creationInfo>
          <agencyID>CI</agencyID>
          <creationTime>2025-01-19T02:17:12.000000Z</creationTime>
        </creationInfo>
      </pick>
      <pick publicID="quakeml:service.scedc.caltech.edu/fdsnws/event/1/query?assocaro=266486757">
        <time>
          <value>2025-01-19T02:13:42.830000Z</value>
          <uncertainty>0.15</uncertainty>
        </time>
        <waveformID networkCode="CI" stationCode="RCR" locationCode="" channelCode="HHE"></waveformID>
        <onset>emergent</onset>
        <phaseHint>S</phaseHint>
        <polarity>undecidable</polarity>
        <evaluationMode>automatic</evaluationMode>
        <evaluationStatus>preliminary</evaluationStatus>
        <creationInfo>
          <agencyID>CI</agencyID>
          <creationTime>2025-01-19T02:17:12.000000Z</creationTime>
        </creationInfo>
      </pick>
      <pick publicID="quakeml:service.scedc.caltech.edu/fdsnws/event/1/query?assocaro=266486765">
        <time>
          <value>2025-01-19T02:13:40.200000Z</value>
          <uncertainty>0.06</uncertainty>
        </time>
        <waveformID networkCode="CI" stationCode="TOR" locationCode="" channelCode="HHZ"></waveformID>
        <onset>impulsive</onset>
        <phaseHint>P</phaseHint>
        <polarity>undecidable</polarity>
        <evaluationMode>automatic</evaluationMode>
        <evaluationStatus>preliminary</evaluationStatus>
        <creationInfo>
          <agencyID>CI</agencyID>
          <creationTime>2025-01-19T02:17:12.000000Z</creationTime>
        </creationInfo>
      </pick>
      <pick publicID="quakeml:service.scedc.caltech.edu/fdsnws/event/1/query?assocaro=266486773">
        <time>
          <value>2025-01-19T02:13:44.910000Z</value>
          <uncertainty>0.15</uncertainty>
        </time>
        <waveformID networkCode="CI" stationCode="TOR" locationCode="" channelCode="HHE"></waveformID>
        <onset>emergent</onset>
        <phaseHint>S</phaseHint>
        <polarity>undecidable</polarity>
        <evaluationMode>automatic</evaluationMode>
        <evaluationStatus>preliminary</evaluationStatus>
        <creationInfo>
          <agencyID>CI</agencyID>
          <creationTime>2025-01-19T02:17:12.000000Z</creationTime>
        </creationInfo>
      </pick>
      <pick publicID="quakeml:service.scedc.caltech.edu/fdsnws/event/1/query?assocaro=266486781">
        <time>
          <value>2025-01-19T02:13:40.650000Z</value>
          <uncertainty>0.06</uncertainty>
        </time>
        <waveformID networkCode="CI" stationCode="PALA" locationCode="" channelCode="HHZ"></waveformID>
        <onset>impulsive</onset>
        <phaseHint>P</phaseHint>
        <polarity>undecidable</polarity>
        <evaluationMode>automatic</evaluationMode>
        <evaluationStatus>preliminary</evaluationStatus>
        <creationInfo>
          <agencyID>CI</agencyID>
          <creationTime>2025-01-19T02:17:12.000000Z</creationTime>
        </creationInfo>
      </pick>
      <pick publicID="quakeml:service.scedc.caltech.edu/fdsnws/event/1/query?assocaro=266486789">
        <time>
          <value>2025-01-19T02:13:40.750000Z</value>
          <uncertainty>0.15</uncertainty>
        </time>
        <waveformID networkCode="CI" stationCode="DGR" locationCode="" channelCode="BHZ"></waveformID>
        <onset>emergent</onset>
        <phaseHint>P</phaseHint>
        <polarity>undecidable</polarity>
        <evaluationMode>automatic</evaluationMode>
        <evaluationStatus>preliminary</evaluationStatus>
        <creationInfo>
          <agencyID>CI</agencyID>
          <creationTime>2025-01-19T02:17:12.000000Z</creationTime>
        </creationInfo>
      </pick>
      <pick publicID="quakeml:service.scedc.caltech.edu/fdsnws/event/1/query?assocaro=266486797">
        <time>
          <value>2025-01-19T02:13:45.710000Z</value>
          <uncertainty>0.15</uncertainty>
        </time>
        <waveformID networkCode="CI" stationCode="DGR" locationCode="" channelCode="HHE"></waveformID>
        <onset>emergent</onset>
        <phaseHint>S</phaseHint>
        <polarity>undecidable</polarity>
        <evaluationMode>automatic</evaluationMode>
        <evaluationStatus>preliminary</evaluationStatus>
        <creationInfo>
          <agencyID>CI</agencyID>
          <creationTime>2025-01-19T02:17:12.000000Z</creationTime>
        </creationInfo>
      </pick>
      <pick publicID="quakeml:service.scedc.caltech.edu/fdsnws/event/1/query?assocaro=266486805">
        <time>
          <value>2025-01-19T02:13:43.760000Z</value>
          <uncertainty>0.15</uncertainty>
        </time>
        <waveformID networkCode="CI" stationCode="CYP" locationCode="" channelCode="HHZ"></waveformID>
        <onset>emergent</onset>
        <phaseHint>P</phaseHint>
        <polarity>undecidable</polarity>
        <evaluationMode>automatic</evaluationMode>
        <evaluationStatus>preliminary</evaluationStatus>
        <creationInfo>
          <agencyID>CI</agencyID>
          <creationTime>2025-01-19T02:17:12.000000Z</creationTime>
        </creationInfo>
      </pick>
      <pick publicID="quakeml:service.scedc.caltech.edu/fdsnws/event/1/query?assocaro=266486813">
        <time>
          <value>2025-01-19T02:13:51.220000Z</value>
          <uncertainty>0.3</uncertainty>
        </time>
        <waveformID networkCode="CI" stationCode="CYP" locationCode="" channelCode="HHE"></waveformID>
        <onset>emergent</onset>
        <phaseHint>S</phaseHint>
        <polarity>undecidable</polarity>
        <evaluationMode>automatic</evaluationMode>
        <evaluationStatus>preliminary</evaluationStatus>
        <creationInfo>
          <agencyID>CI</agencyID>
          <creationTime>2025-01-19T02:17:12.000000Z</creationTime>
        </creationInfo>
      </pick>
      <amplitude publicID="quakeml:service.scedc.caltech.edu/fdsnws/event/1/query?ampid=930514477">
        <genericAmplitude>
          <value>2.5811e-05</value>
        </genericAmplitude>
        <type>AML</type>
        <category>point</category>
        <unit>m</unit>
        <methodID>smi:ci.anss.org/amp/WASF</methodID>
        <snr>7.85139134257044</snr>
        <waveformID networkCode="AZ" stationCode="CRY" locationCode="" channelCode="HHE"></waveformID>
        <scalingTime>
          <value>2025-01-19T02:13:39.550000Z</value>
        </scalingTime>
        <magnitudeHint>ML</magnitudeHint>
        <evaluationMode>automatic</evaluationMode>
        <evaluationStatus>preliminary</evaluationStatus>
      </amplitude>
      <amplitude publicID="quakeml:service.scedc.caltech.edu/fdsnws/event/1/query?ampid=930514469">
        <genericAmplitude>
          <value>4.0561e-05</value>
        </genericAmplitude>
        <type>AML</type>
        <category>point</category>
        <unit>m</unit>
        <methodID>smi:ci.anss.org/amp/WASF</methodID>
        <snr>13.5817323823603</snr>
        <waveformID networkCode="AZ" stationCode="CRY" locationCode="" channelCode="HHN"></waveformID>
        <scalingTime>
          <value>2025-01-19T02:13:39.490000Z</value>
        </scalingTime>
        <magnitudeHint>ML</magnitudeHint>
        <evaluationMode>automatic</evaluationMode>
        <evaluationStatus>preliminary</evaluationStatus>
      </amplitude>
      <amplitude publicID="quakeml:service.scedc.caltech.edu/fdsnws/event/1/query?ampid=930514413">
        <genericAmplitude>
          <value>1.4276e-05</value>
        </genericAmplitude>
        <type>AML</type>
        <category>point</category>
        <unit>m</unit>
        <methodID>smi:ci.anss.org/amp/WASF</methodID>
        <snr>10.5678210909039</snr>
        <waveformID networkCode="AZ" stationCode="FRD" locationCode="" channelCode="HHE"></waveformID>
        <scalingTime>
          <value>2025-01-19T02:13:36.910000Z</value>
        </scalingTime>
        <magnitudeHint>ML</magnitudeHint>
        <evaluationMode>automatic</evaluationMode>
        <evaluationStatus>preliminary</evaluationStatus>
      </amplitude>
      <amplitude publicID="quakeml:service.scedc.caltech.edu/fdsnws/event/1/query?ampid=930514405">
        <genericAmplitude>
          <value>1.4942e-05</value>
        </genericAmplitude>
        <type>AML</type>
        <category>point</category>
        <unit>m</unit>
        <methodID>smi:ci.anss.org/amp/WASF</methodID>
        <snr>15.4709746603717</snr>
        <waveformID networkCode="AZ" stationCode="FRD" locationCode="" channelCode="HHN"></waveformID>
        <scalingTime>
          <value>2025-01-19T02:13:36.830000Z</value>
        </scalingTime>
        <magnitudeHint>ML</magnitudeHint>
        <evaluationMode>automatic</evaluationMode>
        <evaluationStatus>preliminary</evaluationStatus>
      </amplitude>
      <amplitude publicID="quakeml:service.scedc.caltech.edu/fdsnws/event/1/query?ampid=930514461">
        <genericAmplitude>
          <value>1.0172e-05</value>
        </genericAmplitude>
        <type>AML</type>
        <category>point</category>
        <unit>m</unit>
        <methodID>smi:ci.anss.org/amp/WASF</methodID>
        <snr>4.92949341240646</snr>
        <waveformID networkCode="AZ" stationCode="LVA2" locationCode="" channelCode="HHE"></waveformID>
        <scalingTime>
          <value>2025-01-19T02:13:38.980000Z</value>
        </scalingTime>
        <magnitudeHint>ML</magnitudeHint>
        <evaluationMode>automatic</evaluationMode>
        <evaluationStatus>preliminary</evaluationStatus>
      </amplitude>
      <amplitude publicID="quakeml:service.scedc.caltech.edu/fdsnws/event/1/query?ampid=930514453">
        <genericAmplitude>
          <value>1.2002e-05</value>
        </genericAmplitude>
        <type>AML</type>
        <category>point</category>
        <unit>m</unit>
        <methodID>smi:ci.anss.org/amp/WASF</methodID>
        <snr>5.08131344507643</snr>
        <waveformID networkCode="AZ" stationCode="LVA2" locationCode="" channelCode="HHN"></waveformID>
        <scalingTime>
          <value>2025-01-19T02:13:38.850000Z</value>
        </scalingTime>
        <magnitudeHint>ML</magnitudeHint>
        <evaluationMode>automatic</evaluationMode>
        <evaluationStatus>preliminary</evaluationStatus>
      </amplitude>
      <amplitude publicID="quakeml:service.scedc.caltech.edu/fdsnws/event/1/query?ampid=930514501">
        <genericAmplitude>
          <value>1.6371e-05</value>
        </genericAmplitude>
        <type>AML</type>
        <category>point</category>
        <unit>m</unit>
        <methodID>smi:ci.anss.org/amp/WASF</methodID>
        <snr>11.9689020606843</snr>
        <waveformID networkCode="AZ" stationCode="PFO" locationCode="" channelCode="HHE"></waveformID>
        <scalingTime>
          <value>2025-01-19T02:13:40.640000Z</value>
        </scalingTime>
        <magnitudeHint>ML</magnitudeHint>
        <evaluationMode>automatic</evaluationMode>
        <evaluationStatus>preliminary</evaluationStatus>
      </amplitude>
      <amplitude publicID="quakeml:service.scedc.caltech.edu/fdsnws/event/1/query?ampid=930514493">
        <genericAmplitude>
          <value>1.3943e-05</value>
        </genericAmplitude>
        <type>AML</type>
        <category>point</category>
        <unit>m</unit>
        <methodID>smi:ci.anss.org/amp/WASF</methodID>
        <snr>19.8510690843997</snr>
        <waveformID networkCode="AZ" stationCode="PFO" locationCode="" channelCode="HHN"></waveformID>
        <scalingTime>
          <value>2025-01-19T02:13:40.670000Z</value>
        </scalingTime>
        <magnitudeHint>ML</magnitudeHint>
        <evaluationMode>automatic</evaluationMode>
        <evaluationStatus>preliminary</evaluationStatus>
      </amplitude>
      <amplitude publicID="quakeml:service.scedc.caltech.edu/fdsnws/event/1/query?ampid=930514549">
        <genericAmplitude>
          <value>2.8997e-05</value>
        </genericAmplitude>
        <type>AML</type>
        <category>point</category>
        <unit>m</unit>
        <methodID>smi:ci.anss.org/amp/WASF</methodID>
        <snr>15.5391846559585</snr>
        <waveformID networkCode="AZ" stationCode="RDM" locationCode="" channelCode="HHE"></waveformID>
        <scalingTime>
          <value>2025-01-19T02:13:42.670000Z</value>
        </scalingTime>
        <magnitudeHint>ML</magnitudeHint>
        <evaluationMode>automatic</evaluationMode>
        <evaluationStatus>preliminary</evaluationStatus>
      </amplitude>
      <amplitude publicID="quakeml:service.scedc.caltech.edu/fdsnws/event/1/query?ampid=930514541">
        <genericAmplitude>
          <value>2.0324e-05</value>
        </genericAmplitude>
        <type>AML</type>
        <category>point</category>
        <unit>m</unit>
        <methodID>smi:ci.anss.org/amp/WASF</methodID>
        <snr>15.3440196626232</snr>
        <waveformID networkCode="AZ" stationCode="RDM" locationCode="" channelCode="HHN"></waveformID>
        <scalingTime>
          <value>2025-01-19T02:13:42.740000Z</value>
        </scalingTime>
        <magnitudeHint>ML</magnitudeHint>
        <evaluationMode>automatic</evaluationMode>
        <evaluationStatus>preliminary</evaluationStatus>
      </amplitude>
      <amplitude publicID="quakeml:service.scedc.caltech.edu/fdsnws/event/1/query?ampid=930514429">
        <genericAmplitude>
          <value>1.4237e-05</value>
        </genericAmplitude>
        <type>AML</type>
        <category>point</category>
        <unit>m</unit>
        <methodID>smi:ci.anss.org/amp/WASF</methodID>
        <snr>4.15971345038837</snr>
        <waveformID networkCode="AZ" stationCode="SND" locationCode="" channelCode="HHE"></waveformID>
        <scalingTime>
          <value>2025-01-19T02:13:39.170000Z</value>
        </scalingTime>
        <magnitudeHint>ML</magnitudeHint>
        <evaluationMode>automatic</evaluationMode>
        <evaluationStatus>preliminary</evaluationStatus>
      </amplitude>
      <amplitude publicID="quakeml:service.scedc.caltech.edu/fdsnws/event/1/query?ampid=930514421">
        <genericAmplitude>
          <value>1.5914e-05</value>
        </genericAmplitude>
        <type>AML</type>
        <category>point</category>
        <unit>m</unit>
        <methodID>smi:ci.anss.org/amp/WASF</methodID>
        <snr>6.57588444298204</snr>
        <waveformID networkCode="AZ" stationCode="SND" locationCode="" channelCode="HHN"></waveformID>
        <scalingTime>
          <value>2025-01-19T02:13:38.200000Z</value>
        </scalingTime>
        <magnitudeHint>ML</magnitudeHint>
        <evaluationMode>automatic</evaluationMode>
        <evaluationStatus>preliminary</evaluationStatus>
      </amplitude>
      <amplitude publicID="quakeml:service.scedc.caltech.edu/fdsnws/event/1/query?ampid=930514605">
        <genericAmplitude>
          <value>0.00031587</value>
        </genericAmplitude>
        <type>AML</type>
        <category>point</category>
        <unit>m</unit>
        <methodID>smi:ci.anss.org/amp/WAS</methodID>
        <snr>4.2216456762339</snr>
        <waveformID networkCode="CE" stationCode="13141" locationCode="10" channelCode="HNE"></waveformID>
        <scalingTime>
          <value>2025-01-19T02:13:57.230000Z</value>
        </scalingTime>
        <magnitudeHint>ML</magnitudeHint>
        <evaluationMode>automatic</evaluationMode>
        <evaluationStatus>preliminary</evaluationStatus>
      </amplitude>
      <amplitude publicID="quakeml:service.scedc.caltech.edu/fdsnws/event/1/query?ampid=930514613">
        <genericAmplitude>
          <value>8.8277e-05</value>
        </genericAmplitude>
        <type>AML</type>
        <category>point</category>
        <unit>m</unit>
        <methodID>smi:ci.anss.org/amp/WASF</methodID>
        <snr>5.24865536303641</snr>
        <waveformID networkCode="CI" stationCode="BOM" locationCode="" channelCode="HHE"></waveformID>
        <scalingTime>
          <value>2025-01-19T02:13:59.630000Z</value>
        </scalingTime>
        <magnitudeHint>ML</magnitudeHint>
        <evaluationMode>automatic</evaluationMode>
        <evaluationStatus>preliminary</evaluationStatus>
      </amplitude>
      <amplitude publicID="quakeml:service.scedc.caltech.edu/fdsnws/event/1/query?ampid=930514533">
        <genericAmplitude>
          <value>1.607e-05</value>
        </genericAmplitude>
        <type>AML</type>
        <category>point</category>
        <unit>m</unit>
        <methodID>smi:ci.anss.org/amp/WASF</methodID>
        <snr>10.7931751918129</snr>
        <waveformID networkCode="CI" stationCode="BOR" locationCode="" channelCode="HHE"></waveformID>
        <scalingTime>
          <value>2025-01-19T02:13:42.340000Z</value>
        </scalingTime>
        <magnitudeHint>ML</magnitudeHint>
        <evaluationMode>automatic</evaluationMode>
        <evaluationStatus>preliminary</evaluationStatus>
      </amplitude>
      <amplitude publicID="quakeml:service.scedc.caltech.edu/fdsnws/event/1/query?ampid=930514525">
        <genericAmplitude>
          <value>1.3322e-05</value>
        </genericAmplitude>
        <type>AML</type>
        <category>point</category>
        <unit>m</unit>
        <methodID>smi:ci.anss.org/amp/WASF</methodID>
        <snr>7.41612860028806</snr>
        <waveformID networkCode="CI" stationCode="BOR" locationCode="" channelCode="HHN"></waveformID>
        <scalingTime>
          <value>2025-01-19T02:13:42.190000Z</value>
        </scalingTime>
        <magnitudeHint>ML</magnitudeHint>
        <evaluationMode>automatic</evaluationMode>
        <evaluationStatus>preliminary</evaluationStatus>
      </amplitude>
      <amplitude publicID="quakeml:service.scedc.caltech.edu/fdsnws/event/1/query?ampid=930514485">
        <genericAmplitude>
          <value>1.0282e-05</value>
        </genericAmplitude>
        <type>AML</type>
        <category>point</category>
        <unit>m</unit>
        <methodID>smi:ci.anss.org/amp/WASF</methodID>
        <snr>12.626567543391</snr>
        <waveformID networkCode="CI" stationCode="CSH" locationCode="" channelCode="HHE"></waveformID>
        <scalingTime>
          <value>2025-01-19T02:13:40.630000Z</value>
        </scalingTime>
        <magnitudeHint>ML</magnitudeHint>
        <evaluationMode>automatic</evaluationMode>
        <evaluationStatus>preliminary</evaluationStatus>
      </amplitude>
      <amplitude publicID="quakeml:service.scedc.caltech.edu/fdsnws/event/1/query?ampid=930514581">
        <genericAmplitude>
          <value>0.00030118</value>
        </genericAmplitude>
        <type>AML</type>
        <category>point</category>
        <unit>m</unit>
        <methodID>smi:ci.anss.org/amp/WAS</methodID>
        <snr>4.43766410016096</snr>
        <waveformID networkCode="CI" stationCode="CZN" locationCode="" channelCode="HHE"></waveformID>
        <scalingTime>
          <value>2025-01-19T02:13:45.950000Z</value>
        </scalingTime>
        <magnitudeHint>ML</magnitudeHint>
        <evaluationMode>automatic</evaluationMode>
        <evaluationStatus>preliminary</evaluationStatus>
      </amplitude>
      <amplitude publicID="quakeml:service.scedc.caltech.edu/fdsnws/event/1/query?ampid=930514589">
        <genericAmplitude>
          <value>0.00050446</value>
        </genericAmplitude>
        <type>AML</type>
        <category>point</category>
        <unit>m</unit>
        <methodID>smi:ci.anss.org/amp/WAS</methodID>
        <snr>4.59533700713452</snr>
        <waveformID networkCode="CI" stationCode="CZN" locationCode="" channelCode="HNN"></waveformID>
        <scalingTime>
          <value>2025-01-19T02:13:46.050000Z</value>
        </scalingTime>
        <magnitudeHint>ML</magnitudeHint>
        <evaluationMode>automatic</evaluationMode>
        <evaluationStatus>preliminary</evaluationStatus>
      </amplitude>
      <amplitude publicID="quakeml:service.scedc.caltech.edu/fdsnws/event/1/query?ampid=930514445">
        <genericAmplitude>
          <value>3.4516e-05</value>
        </genericAmplitude>
        <type>AML</type>
        <category>point</category>
        <unit>m</unit>
        <methodID>smi:ci.anss.org/amp/WASF</methodID>
        <snr>9.20386719300227</snr>
        <waveformID networkCode="CI" stationCode="DNR" locationCode="" channelCode="HHE"></waveformID>
        <scalingTime>
          <value>2025-01-19T02:13:39.760000Z</value>
        </scalingTime>
        <magnitudeHint>ML</magnitudeHint>
        <evaluationMode>automatic</evaluationMode>
        <evaluationStatus>preliminary</evaluationStatus>
      </amplitude>
      <amplitude publicID="quakeml:service.scedc.caltech.edu/fdsnws/event/1/query?ampid=930514437">
        <genericAmplitude>
          <value>3.451e-05</value>
        </genericAmplitude>
        <type>AML</type>
        <category>point</category>
        <unit>m</unit>
        <methodID>smi:ci.anss.org/amp/WASF</methodID>
        <snr>8.49067927236357</snr>
        <waveformID networkCode="CI" stationCode="DNR" locationCode="" channelCode="HHN"></waveformID>
        <scalingTime>
          <value>2025-01-19T02:13:39.590000Z</value>
        </scalingTime>
        <magnitudeHint>ML</magnitudeHint>
        <evaluationMode>automatic</evaluationMode>
        <evaluationStatus>preliminary</evaluationStatus>
      </amplitude>
      <amplitude publicID="quakeml:service.scedc.caltech.edu/fdsnws/event/1/query?ampid=930514597">
        <genericAmplitude>
          <value>9.6006e-05</value>
        </genericAmplitude>
        <type>AML</type>
        <category>point</category>
        <unit>m</unit>
        <methodID>smi:ci.anss.org/amp/WASF</methodID>
        <snr>4.40923446871158</snr>
        <waveformID networkCode="CI" stationCode="ESI2" locationCode="" channelCode="HHE"></waveformID>
        <scalingTime>
          <value>2025-01-19T02:13:59.680000Z</value>
        </scalingTime>
        <magnitudeHint>ML</magnitudeHint>
        <evaluationMode>automatic</evaluationMode>
        <evaluationStatus>preliminary</evaluationStatus>
      </amplitude>
      <amplitude publicID="quakeml:service.scedc.caltech.edu/fdsnws/event/1/query?ampid=930514517">
        <genericAmplitude>
          <value>1.614e-05</value>
        </genericAmplitude>
        <type>AML</type>
        <category>point</category>
        <unit>m</unit>
        <methodID>smi:ci.anss.org/amp/WASF</methodID>
        <snr>9.11242505351076</snr>
        <waveformID networkCode="CI" stationCode="PLM" locationCode="" channelCode="HHE"></waveformID>
        <scalingTime>
          <value>2025-01-19T02:13:42.170000Z</value>
        </scalingTime>
        <magnitudeHint>ML</magnitudeHint>
        <evaluationMode>automatic</evaluationMode>
        <evaluationStatus>preliminary</evaluationStatus>
      </amplitude>
      <amplitude publicID="quakeml:service.scedc.caltech.edu/fdsnws/event/1/query?ampid=930514509">
        <genericAmplitude>
          <value>1.1585e-05</value>
        </genericAmplitude>
        <type>AML</type>
        <category>point</category>
        <unit>m</unit>
        <methodID>smi:ci.anss.org/amp/WASF</methodID>
        <snr>7.64406696178036</snr>
        <waveformID networkCode="CI" stationCode="PLM" locationCode="" channelCode="HHN"></waveformID>
        <scalingTime>
          <value>2025-01-19T02:13:42.390000Z</value>
        </scalingTime>
        <magnitudeHint>ML</magnitudeHint>
        <evaluationMode>automatic</evaluationMode>
        <evaluationStatus>preliminary</evaluationStatus>
      </amplitude>
      <amplitude publicID="quakeml:service.scedc.caltech.edu/fdsnws/event/1/query?ampid=930514557">
        <genericAmplitude>
          <value>5.5596e-05</value>
        </genericAmplitude>
        <type>AML</type>
        <category>point</category>
        <unit>m</unit>
        <methodID>smi:ci.anss.org/amp/WASF</methodID>
        <snr>4.30410670132291</snr>
        <waveformID networkCode="CI" stationCode="PSD" locationCode="" channelCode="HHE"></waveformID>
        <scalingTime>
          <value>2025-01-19T02:13:41.920000Z</value>
        </scalingTime>
        <magnitudeHint>ML</magnitudeHint>
        <evaluationMode>automatic</evaluationMode>
        <evaluationStatus>preliminary</evaluationStatus>
      </amplitude>
      <amplitude publicID="quakeml:service.scedc.caltech.edu/fdsnws/event/1/query?ampid=930514573">
        <genericAmplitude>
          <value>3.0664e-05</value>
        </genericAmplitude>
        <type>AML</type>
        <category>point</category>
        <unit>m</unit>
        <methodID>smi:ci.anss.org/amp/WASF</methodID>
        <snr>14.6724494724007</snr>
        <waveformID networkCode="CI" stationCode="SLR" locationCode="" channelCode="HHE"></waveformID>
        <scalingTime>
          <value>2025-01-19T02:13:57.940000Z</value>
        </scalingTime>
        <magnitudeHint>ML</magnitudeHint>
        <evaluationMode>automatic</evaluationMode>
        <evaluationStatus>preliminary</evaluationStatus>
      </amplitude>
      <amplitude publicID="quakeml:service.scedc.caltech.edu/fdsnws/event/1/query?ampid=930514565">
        <genericAmplitude>
          <value>2.9155e-05</value>
        </genericAmplitude>
        <type>AML</type>
        <category>point</category>
        <unit>m</unit>
        <methodID>smi:ci.anss.org/amp/WASF</methodID>
        <snr>14.667472633004</snr>
        <waveformID networkCode="CI" stationCode="SLR" locationCode="" channelCode="HHN"></waveformID>
        <scalingTime>
          <value>2025-01-19T02:13:57.840000Z</value>
        </scalingTime>
        <magnitudeHint>ML</magnitudeHint>
        <evaluationMode>automatic</evaluationMode>
        <evaluationStatus>preliminary</evaluationStatus>
      </amplitude>
    </event>
  </eventParameters>
</q:quakeml>
